[
  {
    "stopID": "5",
    "stopQueryDate": "2020-04-30T05:10:00.833Z",
    "Direction": "Outbound",
    "Destination": "Tallaght",
    "Time": "00:02:06",
    "AVLS": "00:02:46",
    "Tram": "3026",
    "Action": "a",
    "Msg Sent": "30/04/2020 06:09:53",
    "Msg Received": "30/04/2020 06:09:53",
    "Msg Processed": "30/04/2020 06:09:53",
    "XML ID": "973",
    "Total Lag": "0.6185597",
    "Create Lag": "0.3471688",
    "Process Lag": "0.2713909"
  },
  {
    "stopID": "5",
    "stopQueryDate": "2020-04-30T05:10:00.833Z",
    "Direction": "Outbound",
    "Destination": "Tallaght",
    "Time": "00:02:06",
    "AVLS": "00:02:46",
    "Tram": "3026",
    "Action": "a",
    "Msg Sent": "30/04/2020 06:09:53",
    "Msg Received": "30/04/2020 06:09:53",
    "Msg Processed": "30/04/2020 06:09:53",
    "XML ID": "973",
    "Total Lag": "0.6185597",
    "Create Lag": "0.3471688",
    "Process Lag": "0.2713909"
  },
  {
    "stopID": "17",
    "stopQueryDate": "2020-04-30T05:10:00.881Z",
    "Direction": "Outbound",
    "Destination": "Tallaght",
    "Time": "00:16:39",
    "AVLS": "00:17:19",
    "Tram": "3023",
    "Action": "a",
    "Msg Sent": "30/04/2020 06:09:53",
    "Msg Received": "30/04/2020 06:09:53",
    "Msg Processed": "30/04/2020 06:09:53",
    "XML ID": "973",
    "Total Lag": "0.6185597",
    "Create Lag": "0.3471688",
    "Process Lag": "0.2713909"
  },
  {
    "stopID": "17",
    "stopQueryDate": "2020-04-30T05:10:00.881Z",
    "Direction": "Outbound",
    "Destination": "Tallaght",
    "Time": "00:16:39",
    "AVLS": "00:17:19",
    "Tram": "3023",
    "Action": "a",
    "Msg Sent": "30/04/2020 06:09:53",
    "Msg Received": "30/04/2020 06:09:53",
    "Msg Processed": "30/04/2020 06:09:53",
    "XML ID": "973",
    "Total Lag": "0.6185597",
    "Create Lag": "0.3471688",
    "Process Lag": "0.2713909"
  },
  {
    "stopID": "3",
    "stopQueryDate": "2020-04-30T05:10:00.898Z",
    "Direction": "Outbound",
    "Destination": "Tallaght",
    "Time": "00:06:10",
    "AVLS": "00:06:50",
    "Tram": "3026",
    "Action": "a",
    "Msg Sent": "30/04/2020 06:09:53",
    "Msg Received": "30/04/2020 06:09:53",
    "Msg Processed": "30/04/2020 06:09:53",
    "XML ID": "973",
    "Total Lag": "0.6185597",
    "Create Lag": "0.3471688",
    "Process Lag": "0.2713909"
  },
  {
    "stopID": "3",
    "stopQueryDate": "2020-04-30T05:10:00.898Z",
    "Direction": "Outbound",
    "Destination": "Tallaght",
    "Time": "00:06:10",
    "AVLS": "00:06:50",
    "Tram": "3026",
    "Action": "a",
    "Msg Sent": "30/04/2020 06:09:53",
    "Msg Received": "30/04/2020 06:09:53",
    "Msg Processed": "30/04/2020 06:09:53",
    "XML ID": "973",
    "Total Lag": "0.6185597",
    "Create Lag": "0.3471688",
    "Process Lag": "0.2713909"
  },
  {
    "stopID": "3",
    "stopQueryDate": "2020-04-30T05:10:00.898Z",
    "Direction": "Outbound",
    "Destination": "Tallaght",
    "Time": "00:06:10",
    "AVLS": "00:06:50",
    "Tram": "3026",
    "Action": "a",
    "Msg Sent": "30/04/2020 06:09:53",
    "Msg Received": "30/04/2020 06:09:53",
    "Msg Processed": "30/04/2020 06:09:53",
    "XML ID": "973",
    "Total Lag": "0.6185597",
    "Create Lag": "0.3471688",
    "Process Lag": "0.2713909"
  },
  {
    "stopID": "6",
    "stopQueryDate": "2020-04-30T05:10:00.915Z",
    "Direction": "Outbound",
    "Destination": "Tallaght",
    "Time": "00:16:44",
    "AVLS": "00:17:24",
    "Tram": "3005",
    "Action": "a",
    "Msg Sent": "30/04/2020 06:09:53",
    "Msg Received": "30/04/2020 06:09:53",
    "Msg Processed": "30/04/2020 06:09:53",
    "XML ID": "973",
    "Total Lag": "0.4891718",
    "Create Lag": "0.3471688",
    "Process Lag": "0.142003"
  },
  {
    "stopID": "6",
    "stopQueryDate": "2020-04-30T05:10:00.915Z",
    "Direction": "Outbound",
    "Destination": "Tallaght",
    "Time": "00:16:44",
    "AVLS": "00:17:24",
    "Tram": "3005",
    "Action": "a",
    "Msg Sent": "30/04/2020 06:09:53",
    "Msg Received": "30/04/2020 06:09:53",
    "Msg Processed": "30/04/2020 06:09:53",
    "XML ID": "973",
    "Total Lag": "0.4891718",
    "Create Lag": "0.3471688",
    "Process Lag": "0.142003"
  },
  {
    "stopID": "6",
    "stopQueryDate": "2020-04-30T05:10:00.915Z",
    "Direction": "Outbound",
    "Destination": "Tallaght",
    "Time": "00:16:44",
    "AVLS": "00:17:24",
    "Tram": "3005",
    "Action": "a",
    "Msg Sent": "30/04/2020 06:09:53",
    "Msg Received": "30/04/2020 06:09:53",
    "Msg Processed": "30/04/2020 06:09:53",
    "XML ID": "973",
    "Total Lag": "0.4891718",
    "Create Lag": "0.3471688",
    "Process Lag": "0.142003"
  },
  {
    "stopID": "6",
    "stopQueryDate": "2020-04-30T05:10:00.915Z",
    "Direction": "Outbound",
    "Destination": "Tallaght",
    "Time": "00:16:44",
    "AVLS": "00:17:24",
    "Tram": "3005",
    "Action": "a",
    "Msg Sent": "30/04/2020 06:09:53",
    "Msg Received": "30/04/2020 06:09:53",
    "Msg Processed": "30/04/2020 06:09:53",
    "XML ID": "973",
    "Total Lag": "0.4891718",
    "Create Lag": "0.3471688",
    "Process Lag": "0.142003"
  },
  {
    "stopID": "10",
    "stopQueryDate": "2020-04-30T05:10:00.951Z",
    "Direction": "Outbound",
    "Destination": "Tallaght",
    "Time": "00:07:36",
    "AVLS": "00:08:16",
    "Tram": "3005",
    "Action": "a",
    "Msg Sent": "30/04/2020 06:09:53",
    "Msg Received": "30/04/2020 06:09:53",
    "Msg Processed": "30/04/2020 06:09:53",
    "XML ID": "973",
    "Total Lag": "0.4722559",
    "Create Lag": "0.3471688",
    "Process Lag": "0.1250871"
  },
  {
    "stopID": "10",
    "stopQueryDate": "2020-04-30T05:10:00.951Z",
    "Direction": "Outbound",
    "Destination": "Tallaght",
    "Time": "00:07:36",
    "AVLS": "00:08:16",
    "Tram": "3005",
    "Action": "a",
    "Msg Sent": "30/04/2020 06:09:53",
    "Msg Received": "30/04/2020 06:09:53",
    "Msg Processed": "30/04/2020 06:09:53",
    "XML ID": "973",
    "Total Lag": "0.4722559",
    "Create Lag": "0.3471688",
    "Process Lag": "0.1250871"
  },
  {
    "stopID": "10",
    "stopQueryDate": "2020-04-30T05:10:00.951Z",
    "Direction": "Outbound",
    "Destination": "Tallaght",
    "Time": "00:07:36",
    "AVLS": "00:08:16",
    "Tram": "3005",
    "Action": "a",
    "Msg Sent": "30/04/2020 06:09:53",
    "Msg Received": "30/04/2020 06:09:53",
    "Msg Processed": "30/04/2020 06:09:53",
    "XML ID": "973",
    "Total Lag": "0.4722559",
    "Create Lag": "0.3471688",
    "Process Lag": "0.1250871"
  },
  {
    "stopID": "10",
    "stopQueryDate": "2020-04-30T05:10:00.951Z",
    "Direction": "Outbound",
    "Destination": "Tallaght",
    "Time": "00:07:36",
    "AVLS": "00:08:16",
    "Tram": "3005",
    "Action": "a",
    "Msg Sent": "30/04/2020 06:09:53",
    "Msg Received": "30/04/2020 06:09:53",
    "Msg Processed": "30/04/2020 06:09:53",
    "XML ID": "973",
    "Total Lag": "0.4722559",
    "Create Lag": "0.3471688",
    "Process Lag": "0.1250871"
  },
  {
    "stopID": "13",
    "stopQueryDate": "2020-04-30T05:10:00.964Z",
    "Direction": "Outbound",
    "Destination": "Tallaght",
    "Time": "00:03:54",
    "AVLS": "00:04:34",
    "Tram": "3005",
    "Action": "a",
    "Msg Sent": "30/04/2020 06:09:53",
    "Msg Received": "30/04/2020 06:09:53",
    "Msg Processed": "30/04/2020 06:09:53",
    "XML ID": "973",
    "Total Lag": "0.4722559",
    "Create Lag": "0.3471688",
    "Process Lag": "0.1250871"
  },
  {
    "stopID": "13",
    "stopQueryDate": "2020-04-30T05:10:00.964Z",
    "Direction": "Outbound",
    "Destination": "Tallaght",
    "Time": "00:03:54",
    "AVLS": "00:04:34",
    "Tram": "3005",
    "Action": "a",
    "Msg Sent": "30/04/2020 06:09:53",
    "Msg Received": "30/04/2020 06:09:53",
    "Msg Processed": "30/04/2020 06:09:53",
    "XML ID": "973",
    "Total Lag": "0.4722559",
    "Create Lag": "0.3471688",
    "Process Lag": "0.1250871"
  },
  {
    "stopID": "13",
    "stopQueryDate": "2020-04-30T05:10:00.964Z",
    "Direction": "Outbound",
    "Destination": "Tallaght",
    "Time": "00:03:54",
    "AVLS": "00:04:34",
    "Tram": "3005",
    "Action": "a",
    "Msg Sent": "30/04/2020 06:09:53",
    "Msg Received": "30/04/2020 06:09:53",
    "Msg Processed": "30/04/2020 06:09:53",
    "XML ID": "973",
    "Total Lag": "0.4722559",
    "Create Lag": "0.3471688",
    "Process Lag": "0.1250871"
  },
  {
    "stopID": "13",
    "stopQueryDate": "2020-04-30T05:10:00.964Z",
    "Direction": "Outbound",
    "Destination": "Tallaght",
    "Time": "00:03:54",
    "AVLS": "00:04:34",
    "Tram": "3005",
    "Action": "a",
    "Msg Sent": "30/04/2020 06:09:53",
    "Msg Received": "30/04/2020 06:09:53",
    "Msg Processed": "30/04/2020 06:09:53",
    "XML ID": "973",
    "Total Lag": "0.4722559",
    "Create Lag": "0.3471688",
    "Process Lag": "0.1250871"
  },
  {
    "stopID": "14",
    "stopQueryDate": "2020-04-30T05:10:00.982Z",
    "Direction": "Outbound",
    "Destination": "Tallaght",
    "Time": "00:02:54",
    "AVLS": "00:03:34",
    "Tram": "3005",
    "Action": "a",
    "Msg Sent": "30/04/2020 06:09:53",
    "Msg Received": "30/04/2020 06:09:53",
    "Msg Processed": "30/04/2020 06:09:53",
    "XML ID": "973",
    "Total Lag": "0.4565512",
    "Create Lag": "0.3471688",
    "Process Lag": "0.1093824"
  },
  {
    "stopID": "14",
    "stopQueryDate": "2020-04-30T05:10:00.982Z",
    "Direction": "Outbound",
    "Destination": "Tallaght",
    "Time": "00:02:54",
    "AVLS": "00:03:34",
    "Tram": "3005",
    "Action": "a",
    "Msg Sent": "30/04/2020 06:09:53",
    "Msg Received": "30/04/2020 06:09:53",
    "Msg Processed": "30/04/2020 06:09:53",
    "XML ID": "973",
    "Total Lag": "0.4565512",
    "Create Lag": "0.3471688",
    "Process Lag": "0.1093824"
  },
  {
    "stopID": "14",
    "stopQueryDate": "2020-04-30T05:10:00.982Z",
    "Direction": "Outbound",
    "Destination": "Tallaght",
    "Time": "00:02:54",
    "AVLS": "00:03:34",
    "Tram": "3005",
    "Action": "a",
    "Msg Sent": "30/04/2020 06:09:53",
    "Msg Received": "30/04/2020 06:09:53",
    "Msg Processed": "30/04/2020 06:09:53",
    "XML ID": "973",
    "Total Lag": "0.4565512",
    "Create Lag": "0.3471688",
    "Process Lag": "0.1093824"
  },
  {
    "stopID": "14",
    "stopQueryDate": "2020-04-30T05:10:00.982Z",
    "Direction": "Outbound",
    "Destination": "Tallaght",
    "Time": "00:02:54",
    "AVLS": "00:03:34",
    "Tram": "3005",
    "Action": "a",
    "Msg Sent": "30/04/2020 06:09:53",
    "Msg Received": "30/04/2020 06:09:53",
    "Msg Processed": "30/04/2020 06:09:53",
    "XML ID": "973",
    "Total Lag": "0.4565512",
    "Create Lag": "0.3471688",
    "Process Lag": "0.1093824"
  },
  {
    "stopID": "7",
    "stopQueryDate": "2020-04-30T05:10:00.992Z",
    "Direction": "Outbound",
    "Destination": "Tallaght",
    "Time": "00:12:41",
    "AVLS": "00:13:21",
    "Tram": "3005",
    "Action": "a",
    "Msg Sent": "30/04/2020 06:09:53",
    "Msg Received": "30/04/2020 06:09:53",
    "Msg Processed": "30/04/2020 06:09:53",
    "XML ID": "973",
    "Total Lag": "0.4891718",
    "Create Lag": "0.3471688",
    "Process Lag": "0.142003"
  },
  {
    "stopID": "7",
    "stopQueryDate": "2020-04-30T05:10:00.992Z",
    "Direction": "Outbound",
    "Destination": "Tallaght",
    "Time": "00:12:41",
    "AVLS": "00:13:21",
    "Tram": "3005",
    "Action": "a",
    "Msg Sent": "30/04/2020 06:09:53",
    "Msg Received": "30/04/2020 06:09:53",
    "Msg Processed": "30/04/2020 06:09:53",
    "XML ID": "973",
    "Total Lag": "0.4891718",
    "Create Lag": "0.3471688",
    "Process Lag": "0.142003"
  },
  {
    "stopID": "7",
    "stopQueryDate": "2020-04-30T05:10:00.992Z",
    "Direction": "Outbound",
    "Destination": "Tallaght",
    "Time": "00:12:41",
    "AVLS": "00:13:21",
    "Tram": "3005",
    "Action": "a",
    "Msg Sent": "30/04/2020 06:09:53",
    "Msg Received": "30/04/2020 06:09:53",
    "Msg Processed": "30/04/2020 06:09:53",
    "XML ID": "973",
    "Total Lag": "0.4891718",
    "Create Lag": "0.3471688",
    "Process Lag": "0.142003"
  },
  {
    "stopID": "7",
    "stopQueryDate": "2020-04-30T05:10:00.992Z",
    "Direction": "Outbound",
    "Destination": "Tallaght",
    "Time": "00:12:41",
    "AVLS": "00:13:21",
    "Tram": "3005",
    "Action": "a",
    "Msg Sent": "30/04/2020 06:09:53",
    "Msg Received": "30/04/2020 06:09:53",
    "Msg Processed": "30/04/2020 06:09:53",
    "XML ID": "973",
    "Total Lag": "0.4891718",
    "Create Lag": "0.3471688",
    "Process Lag": "0.142003"
  },
  {
    "stopID": "11",
    "stopQueryDate": "2020-04-30T05:10:01.016Z",
    "Direction": "Outbound",
    "Destination": "Tallaght",
    "Time": "00:06:40",
    "AVLS": "00:07:20",
    "Tram": "3005",
    "Action": "a",
    "Msg Sent": "30/04/2020 06:09:53",
    "Msg Received": "30/04/2020 06:09:53",
    "Msg Processed": "30/04/2020 06:09:53",
    "XML ID": "973",
    "Total Lag": "0.4722559",
    "Create Lag": "0.3471688",
    "Process Lag": "0.1250871"
  },
  {
    "stopID": "11",
    "stopQueryDate": "2020-04-30T05:10:01.016Z",
    "Direction": "Outbound",
    "Destination": "Tallaght",
    "Time": "00:06:40",
    "AVLS": "00:07:20",
    "Tram": "3005",
    "Action": "a",
    "Msg Sent": "30/04/2020 06:09:53",
    "Msg Received": "30/04/2020 06:09:53",
    "Msg Processed": "30/04/2020 06:09:53",
    "XML ID": "973",
    "Total Lag": "0.4722559",
    "Create Lag": "0.3471688",
    "Process Lag": "0.1250871"
  },
  {
    "stopID": "11",
    "stopQueryDate": "2020-04-30T05:10:01.016Z",
    "Direction": "Outbound",
    "Destination": "Tallaght",
    "Time": "00:06:40",
    "AVLS": "00:07:20",
    "Tram": "3005",
    "Action": "a",
    "Msg Sent": "30/04/2020 06:09:53",
    "Msg Received": "30/04/2020 06:09:53",
    "Msg Processed": "30/04/2020 06:09:53",
    "XML ID": "973",
    "Total Lag": "0.4722559",
    "Create Lag": "0.3471688",
    "Process Lag": "0.1250871"
  },
  {
    "stopID": "11",
    "stopQueryDate": "2020-04-30T05:10:01.016Z",
    "Direction": "Outbound",
    "Destination": "Tallaght",
    "Time": "00:06:40",
    "AVLS": "00:07:20",
    "Tram": "3005",
    "Action": "a",
    "Msg Sent": "30/04/2020 06:09:53",
    "Msg Received": "30/04/2020 06:09:53",
    "Msg Processed": "30/04/2020 06:09:53",
    "XML ID": "973",
    "Total Lag": "0.4722559",
    "Create Lag": "0.3471688",
    "Process Lag": "0.1250871"
  },
  {
    "stopID": "20",
    "stopQueryDate": "2020-04-30T05:10:01.025Z",
    "Direction": "Outbound",
    "Destination": "Tallaght",
    "Time": "00:11:39",
    "AVLS": "00:12:19",
    "Tram": "3023",
    "Action": "a",
    "Msg Sent": "30/04/2020 06:09:53",
    "Msg Received": "30/04/2020 06:09:53",
    "Msg Processed": "30/04/2020 06:09:53",
    "XML ID": "973",
    "Total Lag": "0.6029032",
    "Create Lag": "0.3471688",
    "Process Lag": "0.2557344"
  },
  {
    "stopID": "20",
    "stopQueryDate": "2020-04-30T05:10:01.025Z",
    "Direction": "Outbound",
    "Destination": "Tallaght",
    "Time": "00:11:39",
    "AVLS": "00:12:19",
    "Tram": "3023",
    "Action": "a",
    "Msg Sent": "30/04/2020 06:09:53",
    "Msg Received": "30/04/2020 06:09:53",
    "Msg Processed": "30/04/2020 06:09:53",
    "XML ID": "973",
    "Total Lag": "0.6029032",
    "Create Lag": "0.3471688",
    "Process Lag": "0.2557344"
  },
  {
    "stopID": "22",
    "stopQueryDate": "2020-04-30T05:10:01.035Z",
    "Direction": "Outbound",
    "Destination": "Tallaght",
    "Time": "00:05:59",
    "AVLS": "00:06:39",
    "Tram": "3023",
    "Action": "a",
    "Msg Sent": "30/04/2020 06:09:53",
    "Msg Received": "30/04/2020 06:09:53",
    "Msg Processed": "30/04/2020 06:09:53",
    "XML ID": "973",
    "Total Lag": "0.5873052",
    "Create Lag": "0.3471688",
    "Process Lag": "0.2401364"
  },
  {
    "stopID": "22",
    "stopQueryDate": "2020-04-30T05:10:01.035Z",
    "Direction": "Outbound",
    "Destination": "Tallaght",
    "Time": "00:05:59",
    "AVLS": "00:06:39",
    "Tram": "3023",
    "Action": "a",
    "Msg Sent": "30/04/2020 06:09:53",
    "Msg Received": "30/04/2020 06:09:53",
    "Msg Processed": "30/04/2020 06:09:53",
    "XML ID": "973",
    "Total Lag": "0.5873052",
    "Create Lag": "0.3471688",
    "Process Lag": "0.2401364"
  },
  {
    "stopID": "2",
    "stopQueryDate": "2020-04-30T05:10:01.046Z",
    "Direction": "Outbound",
    "Destination": "Tallaght",
    "Time": "00:07:45",
    "AVLS": "00:08:25",
    "Tram": "3026",
    "Action": "a",
    "Msg Sent": "30/04/2020 06:09:53",
    "Msg Received": "30/04/2020 06:09:53",
    "Msg Processed": "30/04/2020 06:09:53",
    "XML ID": "973",
    "Total Lag": "0.6341375",
    "Create Lag": "0.3471688",
    "Process Lag": "0.2869687"
  },
  {
    "stopID": "2",
    "stopQueryDate": "2020-04-30T05:10:01.046Z",
    "Direction": "Outbound",
    "Destination": "Tallaght",
    "Time": "00:07:45",
    "AVLS": "00:08:25",
    "Tram": "3026",
    "Action": "a",
    "Msg Sent": "30/04/2020 06:09:53",
    "Msg Received": "30/04/2020 06:09:53",
    "Msg Processed": "30/04/2020 06:09:53",
    "XML ID": "973",
    "Total Lag": "0.6341375",
    "Create Lag": "0.3471688",
    "Process Lag": "0.2869687"
  },
  {
    "stopID": "2",
    "stopQueryDate": "2020-04-30T05:10:01.046Z",
    "Direction": "Outbound",
    "Destination": "Tallaght",
    "Time": "00:07:45",
    "AVLS": "00:08:25",
    "Tram": "3026",
    "Action": "a",
    "Msg Sent": "30/04/2020 06:09:53",
    "Msg Received": "30/04/2020 06:09:53",
    "Msg Processed": "30/04/2020 06:09:53",
    "XML ID": "973",
    "Total Lag": "0.6341375",
    "Create Lag": "0.3471688",
    "Process Lag": "0.2869687"
  },
  {
    "stopID": "19",
    "stopQueryDate": "2020-04-30T05:10:01.056Z",
    "Direction": "Outbound",
    "Destination": "Tallaght",
    "Time": "00:13:35",
    "AVLS": "00:14:15",
    "Tram": "3023",
    "Action": "a",
    "Msg Sent": "30/04/2020 06:09:53",
    "Msg Received": "30/04/2020 06:09:53",
    "Msg Processed": "30/04/2020 06:09:53",
    "XML ID": "973",
    "Total Lag": "0.6029032",
    "Create Lag": "0.3471688",
    "Process Lag": "0.2557344"
  },
  {
    "stopID": "19",
    "stopQueryDate": "2020-04-30T05:10:01.056Z",
    "Direction": "Outbound",
    "Destination": "Tallaght",
    "Time": "00:13:35",
    "AVLS": "00:14:15",
    "Tram": "3023",
    "Action": "a",
    "Msg Sent": "30/04/2020 06:09:53",
    "Msg Received": "30/04/2020 06:09:53",
    "Msg Processed": "30/04/2020 06:09:53",
    "XML ID": "973",
    "Total Lag": "0.6029032",
    "Create Lag": "0.3471688",
    "Process Lag": "0.2557344"
  },
  {
    "stopID": "31",
    "stopQueryDate": "2020-04-30T05:10:01.065Z",
    "Direction": "Outbound",
    "Destination": "Bride's Glen",
    "Time": "00:15:43",
    "AVLS": "00:16:23",
    "Tram": "5013",
    "Action": "a",
    "Msg Sent": "30/04/2020 06:09:53",
    "Msg Received": "30/04/2020 06:09:53",
    "Msg Processed": "30/04/2020 06:09:53",
    "XML ID": "974",
    "Total Lag": "0.9707871",
    "Create Lag": "0.6979458",
    "Process Lag": "0.2728413"
  },
  {
    "stopID": "31",
    "stopQueryDate": "2020-04-30T05:10:01.065Z",
    "Direction": "Outbound",
    "Destination": "Bride's Glen",
    "Time": "00:15:43",
    "AVLS": "00:16:23",
    "Tram": "5013",
    "Action": "a",
    "Msg Sent": "30/04/2020 06:09:53",
    "Msg Received": "30/04/2020 06:09:53",
    "Msg Processed": "30/04/2020 06:09:53",
    "XML ID": "974",
    "Total Lag": "0.9707871",
    "Create Lag": "0.6979458",
    "Process Lag": "0.2728413"
  },
  {
    "stopID": "31",
    "stopQueryDate": "2020-04-30T05:10:01.065Z",
    "Direction": "Outbound",
    "Destination": "Bride's Glen",
    "Time": "00:15:43",
    "AVLS": "00:16:23",
    "Tram": "5013",
    "Action": "a",
    "Msg Sent": "30/04/2020 06:09:53",
    "Msg Received": "30/04/2020 06:09:53",
    "Msg Processed": "30/04/2020 06:09:53",
    "XML ID": "974",
    "Total Lag": "0.9707871",
    "Create Lag": "0.6979458",
    "Process Lag": "0.2728413"
  },
  {
    "stopID": "28",
    "stopQueryDate": "2020-04-30T05:10:01.075Z",
    "Direction": "Outbound",
    "Destination": "Bride's Glen",
    "Time": "00:10:41",
    "AVLS": "00:11:21",
    "Tram": "5013",
    "Action": "a",
    "Msg Sent": "30/04/2020 06:09:53",
    "Msg Received": "30/04/2020 06:09:53",
    "Msg Processed": "30/04/2020 06:09:53",
    "XML ID": "974",
    "Total Lag": "0.9551924",
    "Create Lag": "0.6979458",
    "Process Lag": "0.2572466"
  },
  {
    "stopID": "28",
    "stopQueryDate": "2020-04-30T05:10:01.075Z",
    "Direction": "Outbound",
    "Destination": "Bride's Glen",
    "Time": "00:10:41",
    "AVLS": "00:11:21",
    "Tram": "5013",
    "Action": "a",
    "Msg Sent": "30/04/2020 06:09:53",
    "Msg Received": "30/04/2020 06:09:53",
    "Msg Processed": "30/04/2020 06:09:53",
    "XML ID": "974",
    "Total Lag": "0.9551924",
    "Create Lag": "0.6979458",
    "Process Lag": "0.2572466"
  },
  {
    "stopID": "28",
    "stopQueryDate": "2020-04-30T05:10:01.075Z",
    "Direction": "Outbound",
    "Destination": "Bride's Glen",
    "Time": "00:10:41",
    "AVLS": "00:11:21",
    "Tram": "5013",
    "Action": "a",
    "Msg Sent": "30/04/2020 06:09:53",
    "Msg Received": "30/04/2020 06:09:53",
    "Msg Processed": "30/04/2020 06:09:53",
    "XML ID": "974",
    "Total Lag": "0.9551924",
    "Create Lag": "0.6979458",
    "Process Lag": "0.2572466"
  },
  {
    "stopID": "44",
    "stopQueryDate": "2020-04-30T05:10:01.085Z",
    "Direction": "Outbound",
    "Destination": "Bride's Glen",
    "Time": "00:15:09",
    "AVLS": "00:15:49",
    "Tram": "5005",
    "Action": "a",
    "Msg Sent": "30/04/2020 06:09:53",
    "Msg Received": "30/04/2020 06:09:53",
    "Msg Processed": "30/04/2020 06:09:53",
    "XML ID": "974",
    "Total Lag": "0.8903424",
    "Create Lag": "0.6979458",
    "Process Lag": "0.1923966"
  },
  {
    "stopID": "44",
    "stopQueryDate": "2020-04-30T05:10:01.085Z",
    "Direction": "Outbound",
    "Destination": "Bride's Glen",
    "Time": "00:15:09",
    "AVLS": "00:15:49",
    "Tram": "5005",
    "Action": "a",
    "Msg Sent": "30/04/2020 06:09:53",
    "Msg Received": "30/04/2020 06:09:53",
    "Msg Processed": "30/04/2020 06:09:53",
    "XML ID": "974",
    "Total Lag": "0.8903424",
    "Create Lag": "0.6979458",
    "Process Lag": "0.1923966"
  },
  {
    "stopID": "44",
    "stopQueryDate": "2020-04-30T05:10:01.085Z",
    "Direction": "Outbound",
    "Destination": "Bride's Glen",
    "Time": "00:15:09",
    "AVLS": "00:15:49",
    "Tram": "5005",
    "Action": "a",
    "Msg Sent": "30/04/2020 06:09:53",
    "Msg Received": "30/04/2020 06:09:53",
    "Msg Processed": "30/04/2020 06:09:53",
    "XML ID": "974",
    "Total Lag": "0.8903424",
    "Create Lag": "0.6979458",
    "Process Lag": "0.1923966"
  },
  {
    "stopID": "44",
    "stopQueryDate": "2020-04-30T05:10:01.085Z",
    "Direction": "Outbound",
    "Destination": "Bride's Glen",
    "Time": "00:15:09",
    "AVLS": "00:15:49",
    "Tram": "5005",
    "Action": "a",
    "Msg Sent": "30/04/2020 06:09:53",
    "Msg Received": "30/04/2020 06:09:53",
    "Msg Processed": "30/04/2020 06:09:53",
    "XML ID": "974",
    "Total Lag": "0.8903424",
    "Create Lag": "0.6979458",
    "Process Lag": "0.1923966"
  },
  {
    "stopID": "1",
    "stopQueryDate": "2020-04-30T05:10:01.096Z",
    "Direction": "Terminating",
    "Destination": "Tallaght",
    "Time": "00:09:51",
    "AVLS": "00:10:31",
    "Tram": "3026",
    "Action": "a",
    "Msg Sent": "30/04/2020 06:09:53",
    "Msg Received": "30/04/2020 06:09:53",
    "Msg Processed": "30/04/2020 06:09:53",
    "XML ID": "973",
    "Total Lag": "0.6341375",
    "Create Lag": "0.3471688",
    "Process Lag": "0.2869687"
  },
  {
    "stopID": "1",
    "stopQueryDate": "2020-04-30T05:10:01.096Z",
    "Direction": "Terminating",
    "Destination": "Tallaght",
    "Time": "00:09:51",
    "AVLS": "00:10:31",
    "Tram": "3026",
    "Action": "a",
    "Msg Sent": "30/04/2020 06:09:53",
    "Msg Received": "30/04/2020 06:09:53",
    "Msg Processed": "30/04/2020 06:09:53",
    "XML ID": "973",
    "Total Lag": "0.6341375",
    "Create Lag": "0.3471688",
    "Process Lag": "0.2869687"
  },
  {
    "stopID": "1",
    "stopQueryDate": "2020-04-30T05:10:01.096Z",
    "Direction": "Terminating",
    "Destination": "Tallaght",
    "Time": "00:09:51",
    "AVLS": "00:10:31",
    "Tram": "3026",
    "Action": "a",
    "Msg Sent": "30/04/2020 06:09:53",
    "Msg Received": "30/04/2020 06:09:53",
    "Msg Processed": "30/04/2020 06:09:53",
    "XML ID": "973",
    "Total Lag": "0.6341375",
    "Create Lag": "0.3471688",
    "Process Lag": "0.2869687"
  },
  {
    "stopID": "27",
    "stopQueryDate": "2020-04-30T05:10:01.115Z",
    "Direction": "Outbound",
    "Destination": "Bride's Glen",
    "Time": "00:18:45",
    "AVLS": "00:19:25",
    "Tram": "3020",
    "Action": "a",
    "Msg Sent": "30/04/2020 06:09:56",
    "Msg Received": "30/04/2020 06:09:56",
    "Msg Processed": "30/04/2020 06:09:56",
    "XML ID": "975",
    "Total Lag": "0.3821204",
    "Create Lag": "0.319612",
    "Process Lag": "0.0625084"
  },
  {
    "stopID": "27",
    "stopQueryDate": "2020-04-30T05:10:01.115Z",
    "Direction": "Outbound",
    "Destination": "Bride's Glen",
    "Time": "00:18:45",
    "AVLS": "00:19:25",
    "Tram": "3020",
    "Action": "a",
    "Msg Sent": "30/04/2020 06:09:56",
    "Msg Received": "30/04/2020 06:09:56",
    "Msg Processed": "30/04/2020 06:09:56",
    "XML ID": "975",
    "Total Lag": "0.3821204",
    "Create Lag": "0.319612",
    "Process Lag": "0.0625084"
  },
  {
    "stopID": "27",
    "stopQueryDate": "2020-04-30T05:10:01.115Z",
    "Direction": "Outbound",
    "Destination": "Bride's Glen",
    "Time": "00:18:45",
    "AVLS": "00:19:25",
    "Tram": "3020",
    "Action": "a",
    "Msg Sent": "30/04/2020 06:09:56",
    "Msg Received": "30/04/2020 06:09:56",
    "Msg Processed": "30/04/2020 06:09:56",
    "XML ID": "975",
    "Total Lag": "0.3821204",
    "Create Lag": "0.319612",
    "Process Lag": "0.0625084"
  },
  {
    "stopID": "27",
    "stopQueryDate": "2020-04-30T05:10:01.115Z",
    "Direction": "Outbound",
    "Destination": "Bride's Glen",
    "Time": "00:18:45",
    "AVLS": "00:19:25",
    "Tram": "3020",
    "Action": "a",
    "Msg Sent": "30/04/2020 06:09:56",
    "Msg Received": "30/04/2020 06:09:56",
    "Msg Processed": "30/04/2020 06:09:56",
    "XML ID": "975",
    "Total Lag": "0.3821204",
    "Create Lag": "0.319612",
    "Process Lag": "0.0625084"
  },
  {
    "stopID": "16",
    "stopQueryDate": "2020-04-30T05:10:01.125Z",
    "Direction": "Outbound",
    "Destination": "Tallaght",
    "Time": "00:18:27",
    "AVLS": "00:19:07",
    "Tram": "3023",
    "Action": "a",
    "Msg Sent": "30/04/2020 06:09:53",
    "Msg Received": "30/04/2020 06:09:53",
    "Msg Processed": "30/04/2020 06:09:53",
    "XML ID": "973",
    "Total Lag": "0.6185597",
    "Create Lag": "0.3471688",
    "Process Lag": "0.2713909"
  },
  {
    "stopID": "16",
    "stopQueryDate": "2020-04-30T05:10:01.125Z",
    "Direction": "Outbound",
    "Destination": "Tallaght",
    "Time": "00:18:27",
    "AVLS": "00:19:07",
    "Tram": "3023",
    "Action": "a",
    "Msg Sent": "30/04/2020 06:09:53",
    "Msg Received": "30/04/2020 06:09:53",
    "Msg Processed": "30/04/2020 06:09:53",
    "XML ID": "973",
    "Total Lag": "0.6185597",
    "Create Lag": "0.3471688",
    "Process Lag": "0.2713909"
  },
  {
    "stopID": "16",
    "stopQueryDate": "2020-04-30T05:10:01.125Z",
    "Direction": "Outbound",
    "Destination": "Tallaght",
    "Time": "00:18:27",
    "AVLS": "00:19:07",
    "Tram": "3023",
    "Action": "a",
    "Msg Sent": "30/04/2020 06:09:53",
    "Msg Received": "30/04/2020 06:09:53",
    "Msg Processed": "30/04/2020 06:09:53",
    "XML ID": "973",
    "Total Lag": "0.6185597",
    "Create Lag": "0.3471688",
    "Process Lag": "0.2713909"
  },
  {
    "stopID": "36",
    "stopQueryDate": "2020-04-30T05:10:01.133Z",
    "Direction": "Outbound",
    "Destination": "Bride's Glen",
    "Time": "00:03:09",
    "AVLS": "00:03:49",
    "Tram": "5005",
    "Action": "a",
    "Msg Sent": "30/04/2020 06:09:53",
    "Msg Received": "30/04/2020 06:09:53",
    "Msg Processed": "30/04/2020 06:09:53",
    "XML ID": "974",
    "Total Lag": "0.843458",
    "Create Lag": "0.6979458",
    "Process Lag": "0.1455122"
  },
  {
    "stopID": "36",
    "stopQueryDate": "2020-04-30T05:10:01.133Z",
    "Direction": "Outbound",
    "Destination": "Bride's Glen",
    "Time": "00:03:09",
    "AVLS": "00:03:49",
    "Tram": "5005",
    "Action": "a",
    "Msg Sent": "30/04/2020 06:09:53",
    "Msg Received": "30/04/2020 06:09:53",
    "Msg Processed": "30/04/2020 06:09:53",
    "XML ID": "974",
    "Total Lag": "0.843458",
    "Create Lag": "0.6979458",
    "Process Lag": "0.1455122"
  },
  {
    "stopID": "36",
    "stopQueryDate": "2020-04-30T05:10:01.133Z",
    "Direction": "Outbound",
    "Destination": "Bride's Glen",
    "Time": "00:03:09",
    "AVLS": "00:03:49",
    "Tram": "5005",
    "Action": "a",
    "Msg Sent": "30/04/2020 06:09:53",
    "Msg Received": "30/04/2020 06:09:53",
    "Msg Processed": "30/04/2020 06:09:53",
    "XML ID": "974",
    "Total Lag": "0.843458",
    "Create Lag": "0.6979458",
    "Process Lag": "0.1455122"
  },
  {
    "stopID": "36",
    "stopQueryDate": "2020-04-30T05:10:01.133Z",
    "Direction": "Outbound",
    "Destination": "Bride's Glen",
    "Time": "00:03:09",
    "AVLS": "00:03:49",
    "Tram": "5005",
    "Action": "a",
    "Msg Sent": "30/04/2020 06:09:53",
    "Msg Received": "30/04/2020 06:09:53",
    "Msg Processed": "30/04/2020 06:09:53",
    "XML ID": "974",
    "Total Lag": "0.843458",
    "Create Lag": "0.6979458",
    "Process Lag": "0.1455122"
  },
  {
    "stopID": "52",
    "stopQueryDate": "2020-04-30T05:10:01.144Z",
    "Direction": "Outbound",
    "Destination": "Saggart",
    "Time": "00:15:14",
    "AVLS": "00:15:54",
    "Tram": "3019",
    "Action": "a",
    "Msg Sent": "30/04/2020 06:09:53",
    "Msg Received": "30/04/2020 06:09:53",
    "Msg Processed": "30/04/2020 06:09:53",
    "XML ID": "973",
    "Total Lag": "0.5549975",
    "Create Lag": "0.3471688",
    "Process Lag": "0.2078287"
  },
  {
    "stopID": "52",
    "stopQueryDate": "2020-04-30T05:10:01.144Z",
    "Direction": "Outbound",
    "Destination": "Saggart",
    "Time": "00:15:14",
    "AVLS": "00:15:54",
    "Tram": "3019",
    "Action": "a",
    "Msg Sent": "30/04/2020 06:09:53",
    "Msg Received": "30/04/2020 06:09:53",
    "Msg Processed": "30/04/2020 06:09:53",
    "XML ID": "973",
    "Total Lag": "0.5549975",
    "Create Lag": "0.3471688",
    "Process Lag": "0.2078287"
  },
  {
    "stopID": "52",
    "stopQueryDate": "2020-04-30T05:10:01.144Z",
    "Direction": "Outbound",
    "Destination": "Saggart",
    "Time": "00:15:14",
    "AVLS": "00:15:54",
    "Tram": "3019",
    "Action": "a",
    "Msg Sent": "30/04/2020 06:09:53",
    "Msg Received": "30/04/2020 06:09:53",
    "Msg Processed": "30/04/2020 06:09:53",
    "XML ID": "973",
    "Total Lag": "0.5549975",
    "Create Lag": "0.3471688",
    "Process Lag": "0.2078287"
  },
  {
    "stopID": "52",
    "stopQueryDate": "2020-04-30T05:10:01.144Z",
    "Direction": "Outbound",
    "Destination": "Saggart",
    "Time": "00:15:14",
    "AVLS": "00:15:54",
    "Tram": "3019",
    "Action": "a",
    "Msg Sent": "30/04/2020 06:09:53",
    "Msg Received": "30/04/2020 06:09:53",
    "Msg Processed": "30/04/2020 06:09:53",
    "XML ID": "973",
    "Total Lag": "0.5549975",
    "Create Lag": "0.3471688",
    "Process Lag": "0.2078287"
  },
  {
    "stopID": "12",
    "stopQueryDate": "2020-04-30T05:10:01.155Z",
    "Direction": "Outbound",
    "Destination": "Tallaght",
    "Time": "00:05:35",
    "AVLS": "00:06:15",
    "Tram": "3005",
    "Action": "a",
    "Msg Sent": "30/04/2020 06:09:53",
    "Msg Received": "30/04/2020 06:09:53",
    "Msg Processed": "30/04/2020 06:09:53",
    "XML ID": "973",
    "Total Lag": "0.4722559",
    "Create Lag": "0.3471688",
    "Process Lag": "0.1250871"
  },
  {
    "stopID": "12",
    "stopQueryDate": "2020-04-30T05:10:01.155Z",
    "Direction": "Outbound",
    "Destination": "Tallaght",
    "Time": "00:05:35",
    "AVLS": "00:06:15",
    "Tram": "3005",
    "Action": "a",
    "Msg Sent": "30/04/2020 06:09:53",
    "Msg Received": "30/04/2020 06:09:53",
    "Msg Processed": "30/04/2020 06:09:53",
    "XML ID": "973",
    "Total Lag": "0.4722559",
    "Create Lag": "0.3471688",
    "Process Lag": "0.1250871"
  },
  {
    "stopID": "12",
    "stopQueryDate": "2020-04-30T05:10:01.155Z",
    "Direction": "Outbound",
    "Destination": "Tallaght",
    "Time": "00:05:35",
    "AVLS": "00:06:15",
    "Tram": "3005",
    "Action": "a",
    "Msg Sent": "30/04/2020 06:09:53",
    "Msg Received": "30/04/2020 06:09:53",
    "Msg Processed": "30/04/2020 06:09:53",
    "XML ID": "973",
    "Total Lag": "0.4722559",
    "Create Lag": "0.3471688",
    "Process Lag": "0.1250871"
  },
  {
    "stopID": "12",
    "stopQueryDate": "2020-04-30T05:10:01.155Z",
    "Direction": "Outbound",
    "Destination": "Tallaght",
    "Time": "00:05:35",
    "AVLS": "00:06:15",
    "Tram": "3005",
    "Action": "a",
    "Msg Sent": "30/04/2020 06:09:53",
    "Msg Received": "30/04/2020 06:09:53",
    "Msg Processed": "30/04/2020 06:09:53",
    "XML ID": "973",
    "Total Lag": "0.4722559",
    "Create Lag": "0.3471688",
    "Process Lag": "0.1250871"
  },
  {
    "stopID": "24",
    "stopQueryDate": "2020-04-30T05:10:01.164Z",
    "Direction": "Outbound",
    "Destination": "Bride's Glen",
    "Time": "00:12:39",
    "AVLS": "00:13:19",
    "Tram": "3020",
    "Action": "a",
    "Msg Sent": "30/04/2020 06:09:56",
    "Msg Received": "30/04/2020 06:09:56",
    "Msg Processed": "30/04/2020 06:09:56",
    "XML ID": "975",
    "Total Lag": "0.3664976",
    "Create Lag": "0.319612",
    "Process Lag": "0.0468856"
  },
  {
    "stopID": "24",
    "stopQueryDate": "2020-04-30T05:10:01.164Z",
    "Direction": "Outbound",
    "Destination": "Bride's Glen",
    "Time": "00:12:39",
    "AVLS": "00:13:19",
    "Tram": "3020",
    "Action": "a",
    "Msg Sent": "30/04/2020 06:09:56",
    "Msg Received": "30/04/2020 06:09:56",
    "Msg Processed": "30/04/2020 06:09:56",
    "XML ID": "975",
    "Total Lag": "0.3664976",
    "Create Lag": "0.319612",
    "Process Lag": "0.0468856"
  },
  {
    "stopID": "24",
    "stopQueryDate": "2020-04-30T05:10:01.164Z",
    "Direction": "Outbound",
    "Destination": "Bride's Glen",
    "Time": "00:12:39",
    "AVLS": "00:13:19",
    "Tram": "3020",
    "Action": "a",
    "Msg Sent": "30/04/2020 06:09:56",
    "Msg Received": "30/04/2020 06:09:56",
    "Msg Processed": "30/04/2020 06:09:56",
    "XML ID": "975",
    "Total Lag": "0.3664976",
    "Create Lag": "0.319612",
    "Process Lag": "0.0468856"
  },
  {
    "stopID": "24",
    "stopQueryDate": "2020-04-30T05:10:01.164Z",
    "Direction": "Outbound",
    "Destination": "Bride's Glen",
    "Time": "00:12:39",
    "AVLS": "00:13:19",
    "Tram": "3020",
    "Action": "a",
    "Msg Sent": "30/04/2020 06:09:56",
    "Msg Received": "30/04/2020 06:09:56",
    "Msg Processed": "30/04/2020 06:09:56",
    "XML ID": "975",
    "Total Lag": "0.3664976",
    "Create Lag": "0.319612",
    "Process Lag": "0.0468856"
  },
  {
    "stopID": "4",
    "stopQueryDate": "2020-04-30T05:10:01.174Z",
    "Direction": "Outbound",
    "Destination": "Saggart",
    "Time": "00:06:57",
    "AVLS": "00:07:37",
    "Tram": "3019",
    "Action": "a",
    "Msg Sent": "30/04/2020 06:09:53",
    "Msg Received": "30/04/2020 06:09:53",
    "Msg Processed": "30/04/2020 06:09:53",
    "XML ID": "973",
    "Total Lag": "0.5372372",
    "Create Lag": "0.3471688",
    "Process Lag": "0.1900684"
  },
  {
    "stopID": "4",
    "stopQueryDate": "2020-04-30T05:10:01.174Z",
    "Direction": "Outbound",
    "Destination": "Saggart",
    "Time": "00:06:57",
    "AVLS": "00:07:37",
    "Tram": "3019",
    "Action": "a",
    "Msg Sent": "30/04/2020 06:09:53",
    "Msg Received": "30/04/2020 06:09:53",
    "Msg Processed": "30/04/2020 06:09:53",
    "XML ID": "973",
    "Total Lag": "0.5372372",
    "Create Lag": "0.3471688",
    "Process Lag": "0.1900684"
  },
  {
    "stopID": "4",
    "stopQueryDate": "2020-04-30T05:10:01.174Z",
    "Direction": "Outbound",
    "Destination": "Saggart",
    "Time": "00:06:57",
    "AVLS": "00:07:37",
    "Tram": "3019",
    "Action": "a",
    "Msg Sent": "30/04/2020 06:09:53",
    "Msg Received": "30/04/2020 06:09:53",
    "Msg Processed": "30/04/2020 06:09:53",
    "XML ID": "973",
    "Total Lag": "0.5372372",
    "Create Lag": "0.3471688",
    "Process Lag": "0.1900684"
  },
  {
    "stopID": "4",
    "stopQueryDate": "2020-04-30T05:10:01.174Z",
    "Direction": "Outbound",
    "Destination": "Saggart",
    "Time": "00:06:57",
    "AVLS": "00:07:37",
    "Tram": "3019",
    "Action": "a",
    "Msg Sent": "30/04/2020 06:09:53",
    "Msg Received": "30/04/2020 06:09:53",
    "Msg Processed": "30/04/2020 06:09:53",
    "XML ID": "973",
    "Total Lag": "0.5372372",
    "Create Lag": "0.3471688",
    "Process Lag": "0.1900684"
  },
  {
    "stopID": "15",
    "stopQueryDate": "2020-04-30T05:10:01.185Z",
    "Direction": "Outbound",
    "Destination": "Tallaght",
    "Time": "00:00:55",
    "AVLS": "00:01:35",
    "Tram": "3005",
    "Action": "a",
    "Msg Sent": "30/04/2020 06:09:53",
    "Msg Received": "30/04/2020 06:09:53",
    "Msg Processed": "30/04/2020 06:09:53",
    "XML ID": "973",
    "Total Lag": "0.4565512",
    "Create Lag": "0.3471688",
    "Process Lag": "0.1093824"
  },
  {
    "stopID": "15",
    "stopQueryDate": "2020-04-30T05:10:01.185Z",
    "Direction": "Outbound",
    "Destination": "Tallaght",
    "Time": "00:00:55",
    "AVLS": "00:01:35",
    "Tram": "3005",
    "Action": "a",
    "Msg Sent": "30/04/2020 06:09:53",
    "Msg Received": "30/04/2020 06:09:53",
    "Msg Processed": "30/04/2020 06:09:53",
    "XML ID": "973",
    "Total Lag": "0.4565512",
    "Create Lag": "0.3471688",
    "Process Lag": "0.1093824"
  },
  {
    "stopID": "15",
    "stopQueryDate": "2020-04-30T05:10:01.185Z",
    "Direction": "Outbound",
    "Destination": "Tallaght",
    "Time": "00:00:55",
    "AVLS": "00:01:35",
    "Tram": "3005",
    "Action": "a",
    "Msg Sent": "30/04/2020 06:09:53",
    "Msg Received": "30/04/2020 06:09:53",
    "Msg Processed": "30/04/2020 06:09:53",
    "XML ID": "973",
    "Total Lag": "0.4565512",
    "Create Lag": "0.3471688",
    "Process Lag": "0.1093824"
  },
  {
    "stopID": "15",
    "stopQueryDate": "2020-04-30T05:10:01.185Z",
    "Direction": "Outbound",
    "Destination": "Tallaght",
    "Time": "00:00:55",
    "AVLS": "00:01:35",
    "Tram": "3005",
    "Action": "a",
    "Msg Sent": "30/04/2020 06:09:53",
    "Msg Received": "30/04/2020 06:09:53",
    "Msg Processed": "30/04/2020 06:09:53",
    "XML ID": "973",
    "Total Lag": "0.4565512",
    "Create Lag": "0.3471688",
    "Process Lag": "0.1093824"
  },
  {
    "stopID": "8",
    "stopQueryDate": "2020-04-30T05:10:01.195Z",
    "Direction": "Outbound",
    "Destination": "Tallaght",
    "Time": "00:11:07",
    "AVLS": "00:11:47",
    "Tram": "3005",
    "Action": "a",
    "Msg Sent": "30/04/2020 06:09:53",
    "Msg Received": "30/04/2020 06:09:53",
    "Msg Processed": "30/04/2020 06:09:53",
    "XML ID": "973",
    "Total Lag": "0.4878363",
    "Create Lag": "0.3471688",
    "Process Lag": "0.1406675"
  },
  {
    "stopID": "8",
    "stopQueryDate": "2020-04-30T05:10:01.195Z",
    "Direction": "Outbound",
    "Destination": "Tallaght",
    "Time": "00:11:07",
    "AVLS": "00:11:47",
    "Tram": "3005",
    "Action": "a",
    "Msg Sent": "30/04/2020 06:09:53",
    "Msg Received": "30/04/2020 06:09:53",
    "Msg Processed": "30/04/2020 06:09:53",
    "XML ID": "973",
    "Total Lag": "0.4878363",
    "Create Lag": "0.3471688",
    "Process Lag": "0.1406675"
  },
  {
    "stopID": "8",
    "stopQueryDate": "2020-04-30T05:10:01.195Z",
    "Direction": "Outbound",
    "Destination": "Tallaght",
    "Time": "00:11:07",
    "AVLS": "00:11:47",
    "Tram": "3005",
    "Action": "a",
    "Msg Sent": "30/04/2020 06:09:53",
    "Msg Received": "30/04/2020 06:09:53",
    "Msg Processed": "30/04/2020 06:09:53",
    "XML ID": "973",
    "Total Lag": "0.4878363",
    "Create Lag": "0.3471688",
    "Process Lag": "0.1406675"
  },
  {
    "stopID": "8",
    "stopQueryDate": "2020-04-30T05:10:01.195Z",
    "Direction": "Outbound",
    "Destination": "Tallaght",
    "Time": "00:11:07",
    "AVLS": "00:11:47",
    "Tram": "3005",
    "Action": "a",
    "Msg Sent": "30/04/2020 06:09:53",
    "Msg Received": "30/04/2020 06:09:53",
    "Msg Processed": "30/04/2020 06:09:53",
    "XML ID": "973",
    "Total Lag": "0.4878363",
    "Create Lag": "0.3471688",
    "Process Lag": "0.1406675"
  },
  {
    "stopID": "30",
    "stopQueryDate": "2020-04-30T05:10:01.236Z",
    "Direction": "Outbound",
    "Destination": "Bride's Glen",
    "Time": "00:13:55",
    "AVLS": "00:14:35",
    "Tram": "5013",
    "Action": "a",
    "Msg Sent": "30/04/2020 06:09:53",
    "Msg Received": "30/04/2020 06:09:53",
    "Msg Processed": "30/04/2020 06:09:53",
    "XML ID": "974",
    "Total Lag": "0.9551924",
    "Create Lag": "0.6979458",
    "Process Lag": "0.2572466"
  },
  {
    "stopID": "30",
    "stopQueryDate": "2020-04-30T05:10:01.236Z",
    "Direction": "Outbound",
    "Destination": "Bride's Glen",
    "Time": "00:13:55",
    "AVLS": "00:14:35",
    "Tram": "5013",
    "Action": "a",
    "Msg Sent": "30/04/2020 06:09:53",
    "Msg Received": "30/04/2020 06:09:53",
    "Msg Processed": "30/04/2020 06:09:53",
    "XML ID": "974",
    "Total Lag": "0.9551924",
    "Create Lag": "0.6979458",
    "Process Lag": "0.2572466"
  },
  {
    "stopID": "30",
    "stopQueryDate": "2020-04-30T05:10:01.236Z",
    "Direction": "Outbound",
    "Destination": "Bride's Glen",
    "Time": "00:13:55",
    "AVLS": "00:14:35",
    "Tram": "5013",
    "Action": "a",
    "Msg Sent": "30/04/2020 06:09:53",
    "Msg Received": "30/04/2020 06:09:53",
    "Msg Processed": "30/04/2020 06:09:53",
    "XML ID": "974",
    "Total Lag": "0.9551924",
    "Create Lag": "0.6979458",
    "Process Lag": "0.2572466"
  },
  {
    "stopID": "30",
    "stopQueryDate": "2020-04-30T05:10:01.236Z",
    "Direction": "Outbound",
    "Destination": "Bride's Glen",
    "Time": "00:13:55",
    "AVLS": "00:14:35",
    "Tram": "5013",
    "Action": "a",
    "Msg Sent": "30/04/2020 06:09:53",
    "Msg Received": "30/04/2020 06:09:53",
    "Msg Processed": "30/04/2020 06:09:53",
    "XML ID": "974",
    "Total Lag": "0.9551924",
    "Create Lag": "0.6979458",
    "Process Lag": "0.2572466"
  },
  {
    "stopID": "25",
    "stopQueryDate": "2020-04-30T05:10:01.270Z",
    "Direction": "Outbound",
    "Destination": "Bride's Glen",
    "Time": "00:14:37",
    "AVLS": "00:15:17",
    "Tram": "3020",
    "Action": "a",
    "Msg Sent": "30/04/2020 06:09:56",
    "Msg Received": "30/04/2020 06:09:56",
    "Msg Processed": "30/04/2020 06:09:56",
    "XML ID": "975",
    "Total Lag": "0.3821204",
    "Create Lag": "0.319612",
    "Process Lag": "0.0625084"
  },
  {
    "stopID": "25",
    "stopQueryDate": "2020-04-30T05:10:01.270Z",
    "Direction": "Outbound",
    "Destination": "Bride's Glen",
    "Time": "00:14:37",
    "AVLS": "00:15:17",
    "Tram": "3020",
    "Action": "a",
    "Msg Sent": "30/04/2020 06:09:56",
    "Msg Received": "30/04/2020 06:09:56",
    "Msg Processed": "30/04/2020 06:09:56",
    "XML ID": "975",
    "Total Lag": "0.3821204",
    "Create Lag": "0.319612",
    "Process Lag": "0.0625084"
  },
  {
    "stopID": "25",
    "stopQueryDate": "2020-04-30T05:10:01.270Z",
    "Direction": "Outbound",
    "Destination": "Bride's Glen",
    "Time": "00:14:37",
    "AVLS": "00:15:17",
    "Tram": "3020",
    "Action": "a",
    "Msg Sent": "30/04/2020 06:09:56",
    "Msg Received": "30/04/2020 06:09:56",
    "Msg Processed": "30/04/2020 06:09:56",
    "XML ID": "975",
    "Total Lag": "0.3821204",
    "Create Lag": "0.319612",
    "Process Lag": "0.0625084"
  },
  {
    "stopID": "25",
    "stopQueryDate": "2020-04-30T05:10:01.270Z",
    "Direction": "Outbound",
    "Destination": "Bride's Glen",
    "Time": "00:14:37",
    "AVLS": "00:15:17",
    "Tram": "3020",
    "Action": "a",
    "Msg Sent": "30/04/2020 06:09:56",
    "Msg Received": "30/04/2020 06:09:56",
    "Msg Processed": "30/04/2020 06:09:56",
    "XML ID": "975",
    "Total Lag": "0.3821204",
    "Create Lag": "0.319612",
    "Process Lag": "0.0625084"
  },
  {
    "stopID": "57",
    "stopQueryDate": "2020-04-30T05:10:01.279Z",
    "Direction": "Outbound",
    "Destination": "Tallaght",
    "Time": "00:00:00",
    "AVLS": "00:00:37",
    "Tram": "3023",
    "Action": "d",
    "Msg Sent": "30/04/2020 06:09:53",
    "Msg Received": "30/04/2020 06:09:53",
    "Msg Processed": "30/04/2020 06:09:53",
    "XML ID": "973",
    "Total Lag": "0.5873052",
    "Create Lag": "0.3471688",
    "Process Lag": "0.2401364"
  },
  {
    "stopID": "54",
    "stopQueryDate": "2020-04-30T05:10:01.302Z",
    "Direction": "Outbound",
    "Destination": "Tallaght",
    "Time": "00:04:03",
    "AVLS": "00:04:43",
    "Tram": "3023",
    "Action": "a",
    "Msg Sent": "30/04/2020 06:09:53",
    "Msg Received": "30/04/2020 06:09:53",
    "Msg Processed": "30/04/2020 06:09:53",
    "XML ID": "973",
    "Total Lag": "0.5873052",
    "Create Lag": "0.3471688",
    "Process Lag": "0.2401364"
  },
  {
    "stopID": "54",
    "stopQueryDate": "2020-04-30T05:10:01.302Z",
    "Direction": "Outbound",
    "Destination": "Tallaght",
    "Time": "00:04:03",
    "AVLS": "00:04:43",
    "Tram": "3023",
    "Action": "a",
    "Msg Sent": "30/04/2020 06:09:53",
    "Msg Received": "30/04/2020 06:09:53",
    "Msg Processed": "30/04/2020 06:09:53",
    "XML ID": "973",
    "Total Lag": "0.5873052",
    "Create Lag": "0.3471688",
    "Process Lag": "0.2401364"
  },
  {
    "stopID": "56",
    "stopQueryDate": "2020-04-30T05:10:01.310Z",
    "Direction": "Outbound",
    "Destination": "Tallaght",
    "Time": "00:00:36",
    "AVLS": "00:01:16",
    "Tram": "3023",
    "Action": "a",
    "Msg Sent": "30/04/2020 06:09:53",
    "Msg Received": "30/04/2020 06:09:53",
    "Msg Processed": "30/04/2020 06:09:53",
    "XML ID": "973",
    "Total Lag": "0.5873052",
    "Create Lag": "0.3471688",
    "Process Lag": "0.2401364"
  },
  {
    "stopID": "56",
    "stopQueryDate": "2020-04-30T05:10:01.310Z",
    "Direction": "Outbound",
    "Destination": "Tallaght",
    "Time": "00:00:36",
    "AVLS": "00:01:16",
    "Tram": "3023",
    "Action": "a",
    "Msg Sent": "30/04/2020 06:09:53",
    "Msg Received": "30/04/2020 06:09:53",
    "Msg Processed": "30/04/2020 06:09:53",
    "XML ID": "973",
    "Total Lag": "0.5873052",
    "Create Lag": "0.3471688",
    "Process Lag": "0.2401364"
  },
  {
    "stopID": "50",
    "stopQueryDate": "2020-04-30T05:10:01.319Z",
    "Direction": "Outbound",
    "Destination": "Saggart",
    "Time": "00:12:10",
    "AVLS": "00:12:50",
    "Tram": "3019",
    "Action": "a",
    "Msg Sent": "30/04/2020 06:09:53",
    "Msg Received": "30/04/2020 06:09:53",
    "Msg Processed": "30/04/2020 06:09:53",
    "XML ID": "973",
    "Total Lag": "0.5372372",
    "Create Lag": "0.3471688",
    "Process Lag": "0.1900684"
  },
  {
    "stopID": "50",
    "stopQueryDate": "2020-04-30T05:10:01.319Z",
    "Direction": "Outbound",
    "Destination": "Saggart",
    "Time": "00:12:10",
    "AVLS": "00:12:50",
    "Tram": "3019",
    "Action": "a",
    "Msg Sent": "30/04/2020 06:09:53",
    "Msg Received": "30/04/2020 06:09:53",
    "Msg Processed": "30/04/2020 06:09:53",
    "XML ID": "973",
    "Total Lag": "0.5372372",
    "Create Lag": "0.3471688",
    "Process Lag": "0.1900684"
  },
  {
    "stopID": "50",
    "stopQueryDate": "2020-04-30T05:10:01.319Z",
    "Direction": "Outbound",
    "Destination": "Saggart",
    "Time": "00:12:10",
    "AVLS": "00:12:50",
    "Tram": "3019",
    "Action": "a",
    "Msg Sent": "30/04/2020 06:09:53",
    "Msg Received": "30/04/2020 06:09:53",
    "Msg Processed": "30/04/2020 06:09:53",
    "XML ID": "973",
    "Total Lag": "0.5372372",
    "Create Lag": "0.3471688",
    "Process Lag": "0.1900684"
  },
  {
    "stopID": "34",
    "stopQueryDate": "2020-04-30T05:10:01.330Z",
    "Direction": "Outbound",
    "Destination": "Bride's Glen",
    "Time": "00:00:09",
    "AVLS": "00:00:49",
    "Tram": "5005",
    "Action": "a",
    "Msg Sent": "30/04/2020 06:09:53",
    "Msg Received": "30/04/2020 06:09:53",
    "Msg Processed": "30/04/2020 06:09:53",
    "XML ID": "974",
    "Total Lag": "0.843458",
    "Create Lag": "0.6979458",
    "Process Lag": "0.1455122"
  },
  {
    "stopID": "34",
    "stopQueryDate": "2020-04-30T05:10:01.330Z",
    "Direction": "Outbound",
    "Destination": "Bride's Glen",
    "Time": "00:00:09",
    "AVLS": "00:00:49",
    "Tram": "5005",
    "Action": "a",
    "Msg Sent": "30/04/2020 06:09:53",
    "Msg Received": "30/04/2020 06:09:53",
    "Msg Processed": "30/04/2020 06:09:53",
    "XML ID": "974",
    "Total Lag": "0.843458",
    "Create Lag": "0.6979458",
    "Process Lag": "0.1455122"
  },
  {
    "stopID": "34",
    "stopQueryDate": "2020-04-30T05:10:01.330Z",
    "Direction": "Outbound",
    "Destination": "Bride's Glen",
    "Time": "00:00:09",
    "AVLS": "00:00:49",
    "Tram": "5005",
    "Action": "a",
    "Msg Sent": "30/04/2020 06:09:53",
    "Msg Received": "30/04/2020 06:09:53",
    "Msg Processed": "30/04/2020 06:09:53",
    "XML ID": "974",
    "Total Lag": "0.843458",
    "Create Lag": "0.6979458",
    "Process Lag": "0.1455122"
  },
  {
    "stopID": "37",
    "stopQueryDate": "2020-04-30T05:10:01.341Z",
    "Direction": "Outbound",
    "Destination": "Bride's Glen",
    "Time": "00:05:42",
    "AVLS": "00:06:22",
    "Tram": "5005",
    "Action": "a",
    "Msg Sent": "30/04/2020 06:09:53",
    "Msg Received": "30/04/2020 06:09:53",
    "Msg Processed": "30/04/2020 06:09:53",
    "XML ID": "974",
    "Total Lag": "0.843458",
    "Create Lag": "0.6979458",
    "Process Lag": "0.1455122"
  },
  {
    "stopID": "37",
    "stopQueryDate": "2020-04-30T05:10:01.341Z",
    "Direction": "Outbound",
    "Destination": "Bride's Glen",
    "Time": "00:05:42",
    "AVLS": "00:06:22",
    "Tram": "5005",
    "Action": "a",
    "Msg Sent": "30/04/2020 06:09:53",
    "Msg Received": "30/04/2020 06:09:53",
    "Msg Processed": "30/04/2020 06:09:53",
    "XML ID": "974",
    "Total Lag": "0.843458",
    "Create Lag": "0.6979458",
    "Process Lag": "0.1455122"
  },
  {
    "stopID": "37",
    "stopQueryDate": "2020-04-30T05:10:01.341Z",
    "Direction": "Outbound",
    "Destination": "Bride's Glen",
    "Time": "00:05:42",
    "AVLS": "00:06:22",
    "Tram": "5005",
    "Action": "a",
    "Msg Sent": "30/04/2020 06:09:53",
    "Msg Received": "30/04/2020 06:09:53",
    "Msg Processed": "30/04/2020 06:09:53",
    "XML ID": "974",
    "Total Lag": "0.843458",
    "Create Lag": "0.6979458",
    "Process Lag": "0.1455122"
  },
  {
    "stopID": "18",
    "stopQueryDate": "2020-04-30T05:10:01.349Z",
    "Direction": "Outbound",
    "Destination": "Tallaght",
    "Time": "00:14:40",
    "AVLS": "00:15:20",
    "Tram": "3023",
    "Action": "a",
    "Msg Sent": "30/04/2020 06:09:53",
    "Msg Received": "30/04/2020 06:09:53",
    "Msg Processed": "30/04/2020 06:09:53",
    "XML ID": "973",
    "Total Lag": "0.6029032",
    "Create Lag": "0.3471688",
    "Process Lag": "0.2557344"
  },
  {
    "stopID": "18",
    "stopQueryDate": "2020-04-30T05:10:01.349Z",
    "Direction": "Outbound",
    "Destination": "Tallaght",
    "Time": "00:14:40",
    "AVLS": "00:15:20",
    "Tram": "3023",
    "Action": "a",
    "Msg Sent": "30/04/2020 06:09:53",
    "Msg Received": "30/04/2020 06:09:53",
    "Msg Processed": "30/04/2020 06:09:53",
    "XML ID": "973",
    "Total Lag": "0.6029032",
    "Create Lag": "0.3471688",
    "Process Lag": "0.2557344"
  },
  {
    "stopID": "26",
    "stopQueryDate": "2020-04-30T05:10:01.357Z",
    "Direction": "Outbound",
    "Destination": "Bride's Glen",
    "Time": "00:17:17",
    "AVLS": "00:17:57",
    "Tram": "3020",
    "Action": "a",
    "Msg Sent": "30/04/2020 06:09:56",
    "Msg Received": "30/04/2020 06:09:56",
    "Msg Processed": "30/04/2020 06:09:56",
    "XML ID": "975",
    "Total Lag": "0.3821204",
    "Create Lag": "0.319612",
    "Process Lag": "0.0625084"
  },
  {
    "stopID": "26",
    "stopQueryDate": "2020-04-30T05:10:01.357Z",
    "Direction": "Outbound",
    "Destination": "Bride's Glen",
    "Time": "00:17:17",
    "AVLS": "00:17:57",
    "Tram": "3020",
    "Action": "a",
    "Msg Sent": "30/04/2020 06:09:56",
    "Msg Received": "30/04/2020 06:09:56",
    "Msg Processed": "30/04/2020 06:09:56",
    "XML ID": "975",
    "Total Lag": "0.3821204",
    "Create Lag": "0.319612",
    "Process Lag": "0.0625084"
  },
  {
    "stopID": "26",
    "stopQueryDate": "2020-04-30T05:10:01.357Z",
    "Direction": "Outbound",
    "Destination": "Bride's Glen",
    "Time": "00:17:17",
    "AVLS": "00:17:57",
    "Tram": "3020",
    "Action": "a",
    "Msg Sent": "30/04/2020 06:09:56",
    "Msg Received": "30/04/2020 06:09:56",
    "Msg Processed": "30/04/2020 06:09:56",
    "XML ID": "975",
    "Total Lag": "0.3821204",
    "Create Lag": "0.319612",
    "Process Lag": "0.0625084"
  },
  {
    "stopID": "26",
    "stopQueryDate": "2020-04-30T05:10:01.357Z",
    "Direction": "Outbound",
    "Destination": "Bride's Glen",
    "Time": "00:17:17",
    "AVLS": "00:17:57",
    "Tram": "3020",
    "Action": "a",
    "Msg Sent": "30/04/2020 06:09:56",
    "Msg Received": "30/04/2020 06:09:56",
    "Msg Processed": "30/04/2020 06:09:56",
    "XML ID": "975",
    "Total Lag": "0.3821204",
    "Create Lag": "0.319612",
    "Process Lag": "0.0625084"
  },
  {
    "stopID": "32",
    "stopQueryDate": "2020-04-30T05:10:01.361Z",
    "Direction": "Outbound",
    "Destination": "Bride's Glen",
    "Time": "00:17:41",
    "AVLS": "00:18:21",
    "Tram": "5013",
    "Action": "a",
    "Msg Sent": "30/04/2020 06:09:53",
    "Msg Received": "30/04/2020 06:09:53",
    "Msg Processed": "30/04/2020 06:09:53",
    "XML ID": "974",
    "Total Lag": "0.9707871",
    "Create Lag": "0.6979458",
    "Process Lag": "0.2728413"
  },
  {
    "stopID": "32",
    "stopQueryDate": "2020-04-30T05:10:01.361Z",
    "Direction": "Outbound",
    "Destination": "Bride's Glen",
    "Time": "00:17:41",
    "AVLS": "00:18:21",
    "Tram": "5013",
    "Action": "a",
    "Msg Sent": "30/04/2020 06:09:53",
    "Msg Received": "30/04/2020 06:09:53",
    "Msg Processed": "30/04/2020 06:09:53",
    "XML ID": "974",
    "Total Lag": "0.9707871",
    "Create Lag": "0.6979458",
    "Process Lag": "0.2728413"
  },
  {
    "stopID": "32",
    "stopQueryDate": "2020-04-30T05:10:01.361Z",
    "Direction": "Outbound",
    "Destination": "Bride's Glen",
    "Time": "00:17:41",
    "AVLS": "00:18:21",
    "Tram": "5013",
    "Action": "a",
    "Msg Sent": "30/04/2020 06:09:53",
    "Msg Received": "30/04/2020 06:09:53",
    "Msg Processed": "30/04/2020 06:09:53",
    "XML ID": "974",
    "Total Lag": "0.9707871",
    "Create Lag": "0.6979458",
    "Process Lag": "0.2728413"
  },
  {
    "stopID": "48",
    "stopQueryDate": "2020-04-30T05:10:01.370Z",
    "Direction": "Inbound",
    "Destination": "Parnell",
    "Time": "00:11:27",
    "AVLS": "00:12:07",
    "Tram": "5026",
    "Action": "d",
    "Msg Sent": "30/04/2020 06:09:53",
    "Msg Received": "30/04/2020 06:09:53",
    "Msg Processed": "30/04/2020 06:09:54",
    "XML ID": "974",
    "Total Lag": "1.0341874",
    "Create Lag": "0.6979458",
    "Process Lag": "0.3362416"
  },
  {
    "stopID": "48",
    "stopQueryDate": "2020-04-30T05:10:01.370Z",
    "Direction": "Inbound",
    "Destination": "Parnell",
    "Time": "00:11:27",
    "AVLS": "00:12:07",
    "Tram": "5026",
    "Action": "d",
    "Msg Sent": "30/04/2020 06:09:53",
    "Msg Received": "30/04/2020 06:09:53",
    "Msg Processed": "30/04/2020 06:09:54",
    "XML ID": "974",
    "Total Lag": "1.0341874",
    "Create Lag": "0.6979458",
    "Process Lag": "0.3362416"
  },
  {
    "stopID": "40",
    "stopQueryDate": "2020-04-30T05:10:01.379Z",
    "Direction": "Outbound",
    "Destination": "Bride's Glen",
    "Time": "00:10:23",
    "AVLS": "00:11:03",
    "Tram": "5005",
    "Action": "a",
    "Msg Sent": "30/04/2020 06:09:53",
    "Msg Received": "30/04/2020 06:09:53",
    "Msg Processed": "30/04/2020 06:09:53",
    "XML ID": "974",
    "Total Lag": "0.8590681",
    "Create Lag": "0.6979458",
    "Process Lag": "0.1611223"
  },
  {
    "stopID": "40",
    "stopQueryDate": "2020-04-30T05:10:01.379Z",
    "Direction": "Outbound",
    "Destination": "Bride's Glen",
    "Time": "00:10:23",
    "AVLS": "00:11:03",
    "Tram": "5005",
    "Action": "a",
    "Msg Sent": "30/04/2020 06:09:53",
    "Msg Received": "30/04/2020 06:09:53",
    "Msg Processed": "30/04/2020 06:09:53",
    "XML ID": "974",
    "Total Lag": "0.8590681",
    "Create Lag": "0.6979458",
    "Process Lag": "0.1611223"
  },
  {
    "stopID": "40",
    "stopQueryDate": "2020-04-30T05:10:01.379Z",
    "Direction": "Outbound",
    "Destination": "Bride's Glen",
    "Time": "00:10:23",
    "AVLS": "00:11:03",
    "Tram": "5005",
    "Action": "a",
    "Msg Sent": "30/04/2020 06:09:53",
    "Msg Received": "30/04/2020 06:09:53",
    "Msg Processed": "30/04/2020 06:09:53",
    "XML ID": "974",
    "Total Lag": "0.8590681",
    "Create Lag": "0.6979458",
    "Process Lag": "0.1611223"
  },
  {
    "stopID": "47",
    "stopQueryDate": "2020-04-30T05:10:01.388Z",
    "Direction": "Outbound",
    "Destination": "Bride's Glen",
    "Time": "00:15:43",
    "AVLS": "00:16:23",
    "Tram": "4012",
    "Action": "a",
    "Msg Sent": "30/04/2020 06:09:53",
    "Msg Received": "30/04/2020 06:09:53",
    "Msg Processed": "30/04/2020 06:09:53",
    "XML ID": "974",
    "Total Lag": "0.843458",
    "Create Lag": "0.6979458",
    "Process Lag": "0.1455122"
  },
  {
    "stopID": "47",
    "stopQueryDate": "2020-04-30T05:10:01.388Z",
    "Direction": "Outbound",
    "Destination": "Bride's Glen",
    "Time": "00:15:43",
    "AVLS": "00:16:23",
    "Tram": "4012",
    "Action": "a",
    "Msg Sent": "30/04/2020 06:09:53",
    "Msg Received": "30/04/2020 06:09:53",
    "Msg Processed": "30/04/2020 06:09:53",
    "XML ID": "974",
    "Total Lag": "0.843458",
    "Create Lag": "0.6979458",
    "Process Lag": "0.1455122"
  },
  {
    "stopID": "47",
    "stopQueryDate": "2020-04-30T05:10:01.388Z",
    "Direction": "Outbound",
    "Destination": "Bride's Glen",
    "Time": "00:15:43",
    "AVLS": "00:16:23",
    "Tram": "4012",
    "Action": "a",
    "Msg Sent": "30/04/2020 06:09:53",
    "Msg Received": "30/04/2020 06:09:53",
    "Msg Processed": "30/04/2020 06:09:53",
    "XML ID": "974",
    "Total Lag": "0.843458",
    "Create Lag": "0.6979458",
    "Process Lag": "0.1455122"
  },
  {
    "stopID": "39",
    "stopQueryDate": "2020-04-30T05:10:01.399Z",
    "Direction": "Outbound",
    "Destination": "Bride's Glen",
    "Time": "00:08:55",
    "AVLS": "00:09:35",
    "Tram": "5005",
    "Action": "a",
    "Msg Sent": "30/04/2020 06:09:53",
    "Msg Received": "30/04/2020 06:09:53",
    "Msg Processed": "30/04/2020 06:09:53",
    "XML ID": "974",
    "Total Lag": "0.8590681",
    "Create Lag": "0.6979458",
    "Process Lag": "0.1611223"
  },
  {
    "stopID": "39",
    "stopQueryDate": "2020-04-30T05:10:01.399Z",
    "Direction": "Outbound",
    "Destination": "Bride's Glen",
    "Time": "00:08:55",
    "AVLS": "00:09:35",
    "Tram": "5005",
    "Action": "a",
    "Msg Sent": "30/04/2020 06:09:53",
    "Msg Received": "30/04/2020 06:09:53",
    "Msg Processed": "30/04/2020 06:09:53",
    "XML ID": "974",
    "Total Lag": "0.8590681",
    "Create Lag": "0.6979458",
    "Process Lag": "0.1611223"
  },
  {
    "stopID": "39",
    "stopQueryDate": "2020-04-30T05:10:01.399Z",
    "Direction": "Outbound",
    "Destination": "Bride's Glen",
    "Time": "00:08:55",
    "AVLS": "00:09:35",
    "Tram": "5005",
    "Action": "a",
    "Msg Sent": "30/04/2020 06:09:53",
    "Msg Received": "30/04/2020 06:09:53",
    "Msg Processed": "30/04/2020 06:09:53",
    "XML ID": "974",
    "Total Lag": "0.8590681",
    "Create Lag": "0.6979458",
    "Process Lag": "0.1611223"
  },
  {
    "stopID": "38",
    "stopQueryDate": "2020-04-30T05:10:01.403Z",
    "Direction": "Outbound",
    "Destination": "Bride's Glen",
    "Time": "00:07:10",
    "AVLS": "00:07:50",
    "Tram": "5005",
    "Action": "a",
    "Msg Sent": "30/04/2020 06:09:53",
    "Msg Received": "30/04/2020 06:09:53",
    "Msg Processed": "30/04/2020 06:09:53",
    "XML ID": "974",
    "Total Lag": "0.8590681",
    "Create Lag": "0.6979458",
    "Process Lag": "0.1611223"
  },
  {
    "stopID": "38",
    "stopQueryDate": "2020-04-30T05:10:01.403Z",
    "Direction": "Outbound",
    "Destination": "Bride's Glen",
    "Time": "00:07:10",
    "AVLS": "00:07:50",
    "Tram": "5005",
    "Action": "a",
    "Msg Sent": "30/04/2020 06:09:53",
    "Msg Received": "30/04/2020 06:09:53",
    "Msg Processed": "30/04/2020 06:09:53",
    "XML ID": "974",
    "Total Lag": "0.8590681",
    "Create Lag": "0.6979458",
    "Process Lag": "0.1611223"
  },
  {
    "stopID": "38",
    "stopQueryDate": "2020-04-30T05:10:01.403Z",
    "Direction": "Outbound",
    "Destination": "Bride's Glen",
    "Time": "00:07:10",
    "AVLS": "00:07:50",
    "Tram": "5005",
    "Action": "a",
    "Msg Sent": "30/04/2020 06:09:53",
    "Msg Received": "30/04/2020 06:09:53",
    "Msg Processed": "30/04/2020 06:09:53",
    "XML ID": "974",
    "Total Lag": "0.8590681",
    "Create Lag": "0.6979458",
    "Process Lag": "0.1611223"
  },
  {
    "stopID": "46",
    "stopQueryDate": "2020-04-30T05:10:01.412Z",
    "Direction": "Outbound",
    "Destination": "Bride's Glen",
    "Time": "00:18:00",
    "AVLS": "00:18:40",
    "Tram": "5005",
    "Action": "a",
    "Msg Sent": "30/04/2020 06:09:53",
    "Msg Received": "30/04/2020 06:09:53",
    "Msg Processed": "30/04/2020 06:09:53",
    "XML ID": "974",
    "Total Lag": "0.8903424",
    "Create Lag": "0.6979458",
    "Process Lag": "0.1923966"
  },
  {
    "stopID": "46",
    "stopQueryDate": "2020-04-30T05:10:01.412Z",
    "Direction": "Outbound",
    "Destination": "Bride's Glen",
    "Time": "00:18:00",
    "AVLS": "00:18:40",
    "Tram": "5005",
    "Action": "a",
    "Msg Sent": "30/04/2020 06:09:53",
    "Msg Received": "30/04/2020 06:09:53",
    "Msg Processed": "30/04/2020 06:09:53",
    "XML ID": "974",
    "Total Lag": "0.8903424",
    "Create Lag": "0.6979458",
    "Process Lag": "0.1923966"
  },
  {
    "stopID": "46",
    "stopQueryDate": "2020-04-30T05:10:01.412Z",
    "Direction": "Outbound",
    "Destination": "Bride's Glen",
    "Time": "00:18:00",
    "AVLS": "00:18:40",
    "Tram": "5005",
    "Action": "a",
    "Msg Sent": "30/04/2020 06:09:53",
    "Msg Received": "30/04/2020 06:09:53",
    "Msg Processed": "30/04/2020 06:09:53",
    "XML ID": "974",
    "Total Lag": "0.8903424",
    "Create Lag": "0.6979458",
    "Process Lag": "0.1923966"
  },
  {
    "stopID": "46",
    "stopQueryDate": "2020-04-30T05:10:01.412Z",
    "Direction": "Outbound",
    "Destination": "Bride's Glen",
    "Time": "00:18:00",
    "AVLS": "00:18:40",
    "Tram": "5005",
    "Action": "a",
    "Msg Sent": "30/04/2020 06:09:53",
    "Msg Received": "30/04/2020 06:09:53",
    "Msg Processed": "30/04/2020 06:09:53",
    "XML ID": "974",
    "Total Lag": "0.8903424",
    "Create Lag": "0.6979458",
    "Process Lag": "0.1923966"
  },
  {
    "stopID": "51",
    "stopQueryDate": "2020-04-30T05:10:01.421Z",
    "Direction": "Outbound",
    "Destination": "Saggart",
    "Time": "00:13:57",
    "AVLS": "00:14:37",
    "Tram": "3019",
    "Action": "a",
    "Msg Sent": "30/04/2020 06:09:53",
    "Msg Received": "30/04/2020 06:09:53",
    "Msg Processed": "30/04/2020 06:09:53",
    "XML ID": "973",
    "Total Lag": "0.5549975",
    "Create Lag": "0.3471688",
    "Process Lag": "0.2078287"
  },
  {
    "stopID": "51",
    "stopQueryDate": "2020-04-30T05:10:01.421Z",
    "Direction": "Outbound",
    "Destination": "Saggart",
    "Time": "00:13:57",
    "AVLS": "00:14:37",
    "Tram": "3019",
    "Action": "a",
    "Msg Sent": "30/04/2020 06:09:53",
    "Msg Received": "30/04/2020 06:09:53",
    "Msg Processed": "30/04/2020 06:09:53",
    "XML ID": "973",
    "Total Lag": "0.5549975",
    "Create Lag": "0.3471688",
    "Process Lag": "0.2078287"
  },
  {
    "stopID": "51",
    "stopQueryDate": "2020-04-30T05:10:01.421Z",
    "Direction": "Outbound",
    "Destination": "Saggart",
    "Time": "00:13:57",
    "AVLS": "00:14:37",
    "Tram": "3019",
    "Action": "a",
    "Msg Sent": "30/04/2020 06:09:53",
    "Msg Received": "30/04/2020 06:09:53",
    "Msg Processed": "30/04/2020 06:09:53",
    "XML ID": "973",
    "Total Lag": "0.5549975",
    "Create Lag": "0.3471688",
    "Process Lag": "0.2078287"
  },
  {
    "stopID": "51",
    "stopQueryDate": "2020-04-30T05:10:01.421Z",
    "Direction": "Outbound",
    "Destination": "Saggart",
    "Time": "00:13:57",
    "AVLS": "00:14:37",
    "Tram": "3019",
    "Action": "a",
    "Msg Sent": "30/04/2020 06:09:53",
    "Msg Received": "30/04/2020 06:09:53",
    "Msg Processed": "30/04/2020 06:09:53",
    "XML ID": "973",
    "Total Lag": "0.5549975",
    "Create Lag": "0.3471688",
    "Process Lag": "0.2078287"
  },
  {
    "stopID": "21",
    "stopQueryDate": "2020-04-30T05:10:01.430Z",
    "Direction": "Outbound",
    "Destination": "Tallaght",
    "Time": "00:09:27",
    "AVLS": "00:10:07",
    "Tram": "3023",
    "Action": "a",
    "Msg Sent": "30/04/2020 06:09:53",
    "Msg Received": "30/04/2020 06:09:53",
    "Msg Processed": "30/04/2020 06:09:53",
    "XML ID": "973",
    "Total Lag": "0.6029032",
    "Create Lag": "0.3471688",
    "Process Lag": "0.2557344"
  },
  {
    "stopID": "21",
    "stopQueryDate": "2020-04-30T05:10:01.430Z",
    "Direction": "Outbound",
    "Destination": "Tallaght",
    "Time": "00:09:27",
    "AVLS": "00:10:07",
    "Tram": "3023",
    "Action": "a",
    "Msg Sent": "30/04/2020 06:09:53",
    "Msg Received": "30/04/2020 06:09:53",
    "Msg Processed": "30/04/2020 06:09:53",
    "XML ID": "973",
    "Total Lag": "0.6029032",
    "Create Lag": "0.3471688",
    "Process Lag": "0.2557344"
  },
  {
    "stopID": "9",
    "stopQueryDate": "2020-04-30T05:10:01.438Z",
    "Direction": "Outbound",
    "Destination": "Tallaght",
    "Time": "00:08:52",
    "AVLS": "00:09:32",
    "Tram": "3005",
    "Action": "a",
    "Msg Sent": "30/04/2020 06:09:53",
    "Msg Received": "30/04/2020 06:09:53",
    "Msg Processed": "30/04/2020 06:09:53",
    "XML ID": "973",
    "Total Lag": "0.4722559",
    "Create Lag": "0.3471688",
    "Process Lag": "0.1250871"
  },
  {
    "stopID": "9",
    "stopQueryDate": "2020-04-30T05:10:01.438Z",
    "Direction": "Outbound",
    "Destination": "Tallaght",
    "Time": "00:08:52",
    "AVLS": "00:09:32",
    "Tram": "3005",
    "Action": "a",
    "Msg Sent": "30/04/2020 06:09:53",
    "Msg Received": "30/04/2020 06:09:53",
    "Msg Processed": "30/04/2020 06:09:53",
    "XML ID": "973",
    "Total Lag": "0.4722559",
    "Create Lag": "0.3471688",
    "Process Lag": "0.1250871"
  },
  {
    "stopID": "9",
    "stopQueryDate": "2020-04-30T05:10:01.438Z",
    "Direction": "Outbound",
    "Destination": "Tallaght",
    "Time": "00:08:52",
    "AVLS": "00:09:32",
    "Tram": "3005",
    "Action": "a",
    "Msg Sent": "30/04/2020 06:09:53",
    "Msg Received": "30/04/2020 06:09:53",
    "Msg Processed": "30/04/2020 06:09:53",
    "XML ID": "973",
    "Total Lag": "0.4722559",
    "Create Lag": "0.3471688",
    "Process Lag": "0.1250871"
  },
  {
    "stopID": "9",
    "stopQueryDate": "2020-04-30T05:10:01.438Z",
    "Direction": "Outbound",
    "Destination": "Tallaght",
    "Time": "00:08:52",
    "AVLS": "00:09:32",
    "Tram": "3005",
    "Action": "a",
    "Msg Sent": "30/04/2020 06:09:53",
    "Msg Received": "30/04/2020 06:09:53",
    "Msg Processed": "30/04/2020 06:09:53",
    "XML ID": "973",
    "Total Lag": "0.4722559",
    "Create Lag": "0.3471688",
    "Process Lag": "0.1250871"
  },
  {
    "stopID": "49",
    "stopQueryDate": "2020-04-30T05:10:01.451Z",
    "Direction": "Outbound",
    "Destination": "Saggart",
    "Time": "00:10:24",
    "AVLS": "00:11:04",
    "Tram": "3019",
    "Action": "a",
    "Msg Sent": "30/04/2020 06:09:53",
    "Msg Received": "30/04/2020 06:09:53",
    "Msg Processed": "30/04/2020 06:09:53",
    "XML ID": "973",
    "Total Lag": "0.5372372",
    "Create Lag": "0.3471688",
    "Process Lag": "0.1900684"
  },
  {
    "stopID": "49",
    "stopQueryDate": "2020-04-30T05:10:01.451Z",
    "Direction": "Outbound",
    "Destination": "Saggart",
    "Time": "00:10:24",
    "AVLS": "00:11:04",
    "Tram": "3019",
    "Action": "a",
    "Msg Sent": "30/04/2020 06:09:53",
    "Msg Received": "30/04/2020 06:09:53",
    "Msg Processed": "30/04/2020 06:09:53",
    "XML ID": "973",
    "Total Lag": "0.5372372",
    "Create Lag": "0.3471688",
    "Process Lag": "0.1900684"
  },
  {
    "stopID": "49",
    "stopQueryDate": "2020-04-30T05:10:01.451Z",
    "Direction": "Outbound",
    "Destination": "Saggart",
    "Time": "00:10:24",
    "AVLS": "00:11:04",
    "Tram": "3019",
    "Action": "a",
    "Msg Sent": "30/04/2020 06:09:53",
    "Msg Received": "30/04/2020 06:09:53",
    "Msg Processed": "30/04/2020 06:09:53",
    "XML ID": "973",
    "Total Lag": "0.5372372",
    "Create Lag": "0.3471688",
    "Process Lag": "0.1900684"
  },
  {
    "stopID": "49",
    "stopQueryDate": "2020-04-30T05:10:01.451Z",
    "Direction": "Outbound",
    "Destination": "Saggart",
    "Time": "00:10:24",
    "AVLS": "00:11:04",
    "Tram": "3019",
    "Action": "a",
    "Msg Sent": "30/04/2020 06:09:53",
    "Msg Received": "30/04/2020 06:09:53",
    "Msg Processed": "30/04/2020 06:09:53",
    "XML ID": "973",
    "Total Lag": "0.5372372",
    "Create Lag": "0.3471688",
    "Process Lag": "0.1900684"
  },
  {
    "stopID": "35",
    "stopQueryDate": "2020-04-30T05:10:01.456Z",
    "Direction": "Outbound",
    "Destination": "Bride's Glen",
    "Time": "00:01:48",
    "AVLS": "00:02:28",
    "Tram": "5005",
    "Action": "a",
    "Msg Sent": "30/04/2020 06:09:53",
    "Msg Received": "30/04/2020 06:09:53",
    "Msg Processed": "30/04/2020 06:09:53",
    "XML ID": "974",
    "Total Lag": "0.843458",
    "Create Lag": "0.6979458",
    "Process Lag": "0.1455122"
  },
  {
    "stopID": "35",
    "stopQueryDate": "2020-04-30T05:10:01.456Z",
    "Direction": "Outbound",
    "Destination": "Bride's Glen",
    "Time": "00:01:48",
    "AVLS": "00:02:28",
    "Tram": "5005",
    "Action": "a",
    "Msg Sent": "30/04/2020 06:09:53",
    "Msg Received": "30/04/2020 06:09:53",
    "Msg Processed": "30/04/2020 06:09:53",
    "XML ID": "974",
    "Total Lag": "0.843458",
    "Create Lag": "0.6979458",
    "Process Lag": "0.1455122"
  },
  {
    "stopID": "35",
    "stopQueryDate": "2020-04-30T05:10:01.456Z",
    "Direction": "Outbound",
    "Destination": "Bride's Glen",
    "Time": "00:01:48",
    "AVLS": "00:02:28",
    "Tram": "5005",
    "Action": "a",
    "Msg Sent": "30/04/2020 06:09:53",
    "Msg Received": "30/04/2020 06:09:53",
    "Msg Processed": "30/04/2020 06:09:53",
    "XML ID": "974",
    "Total Lag": "0.843458",
    "Create Lag": "0.6979458",
    "Process Lag": "0.1455122"
  },
  {
    "stopID": "35",
    "stopQueryDate": "2020-04-30T05:10:01.456Z",
    "Direction": "Outbound",
    "Destination": "Bride's Glen",
    "Time": "00:01:48",
    "AVLS": "00:02:28",
    "Tram": "5005",
    "Action": "a",
    "Msg Sent": "30/04/2020 06:09:53",
    "Msg Received": "30/04/2020 06:09:53",
    "Msg Processed": "30/04/2020 06:09:53",
    "XML ID": "974",
    "Total Lag": "0.843458",
    "Create Lag": "0.6979458",
    "Process Lag": "0.1455122"
  },
  {
    "stopID": "55",
    "stopQueryDate": "2020-04-30T05:10:01.463Z",
    "Direction": "Outbound",
    "Destination": "Tallaght",
    "Time": "00:02:35",
    "AVLS": "00:03:15",
    "Tram": "3023",
    "Action": "a",
    "Msg Sent": "30/04/2020 06:09:53",
    "Msg Received": "30/04/2020 06:09:53",
    "Msg Processed": "30/04/2020 06:09:53",
    "XML ID": "973",
    "Total Lag": "0.5873052",
    "Create Lag": "0.3471688",
    "Process Lag": "0.2401364"
  },
  {
    "stopID": "55",
    "stopQueryDate": "2020-04-30T05:10:01.463Z",
    "Direction": "Outbound",
    "Destination": "Tallaght",
    "Time": "00:02:35",
    "AVLS": "00:03:15",
    "Tram": "3023",
    "Action": "a",
    "Msg Sent": "30/04/2020 06:09:53",
    "Msg Received": "30/04/2020 06:09:53",
    "Msg Processed": "30/04/2020 06:09:53",
    "XML ID": "973",
    "Total Lag": "0.5873052",
    "Create Lag": "0.3471688",
    "Process Lag": "0.2401364"
  },
  {
    "stopID": "45",
    "stopQueryDate": "2020-04-30T05:10:01.472Z",
    "Direction": "Outbound",
    "Destination": "Bride's Glen",
    "Time": "00:16:37",
    "AVLS": "00:17:17",
    "Tram": "5005",
    "Action": "a",
    "Msg Sent": "30/04/2020 06:09:53",
    "Msg Received": "30/04/2020 06:09:53",
    "Msg Processed": "30/04/2020 06:09:53",
    "XML ID": "974",
    "Total Lag": "0.8903424",
    "Create Lag": "0.6979458",
    "Process Lag": "0.1923966"
  },
  {
    "stopID": "45",
    "stopQueryDate": "2020-04-30T05:10:01.472Z",
    "Direction": "Outbound",
    "Destination": "Bride's Glen",
    "Time": "00:16:37",
    "AVLS": "00:17:17",
    "Tram": "5005",
    "Action": "a",
    "Msg Sent": "30/04/2020 06:09:53",
    "Msg Received": "30/04/2020 06:09:53",
    "Msg Processed": "30/04/2020 06:09:53",
    "XML ID": "974",
    "Total Lag": "0.8903424",
    "Create Lag": "0.6979458",
    "Process Lag": "0.1923966"
  },
  {
    "stopID": "45",
    "stopQueryDate": "2020-04-30T05:10:01.472Z",
    "Direction": "Outbound",
    "Destination": "Bride's Glen",
    "Time": "00:16:37",
    "AVLS": "00:17:17",
    "Tram": "5005",
    "Action": "a",
    "Msg Sent": "30/04/2020 06:09:53",
    "Msg Received": "30/04/2020 06:09:53",
    "Msg Processed": "30/04/2020 06:09:53",
    "XML ID": "974",
    "Total Lag": "0.8903424",
    "Create Lag": "0.6979458",
    "Process Lag": "0.1923966"
  },
  {
    "stopID": "45",
    "stopQueryDate": "2020-04-30T05:10:01.472Z",
    "Direction": "Outbound",
    "Destination": "Bride's Glen",
    "Time": "00:16:37",
    "AVLS": "00:17:17",
    "Tram": "5005",
    "Action": "a",
    "Msg Sent": "30/04/2020 06:09:53",
    "Msg Received": "30/04/2020 06:09:53",
    "Msg Processed": "30/04/2020 06:09:53",
    "XML ID": "974",
    "Total Lag": "0.8903424",
    "Create Lag": "0.6979458",
    "Process Lag": "0.1923966"
  },
  {
    "stopID": "33",
    "stopQueryDate": "2020-04-30T05:10:01.476Z",
    "Direction": "Outbound",
    "Destination": "Bride's Glen",
    "Time": "00:19:07",
    "AVLS": "00:19:47",
    "Tram": "5013",
    "Action": "a",
    "Msg Sent": "30/04/2020 06:09:53",
    "Msg Received": "30/04/2020 06:09:53",
    "Msg Processed": "30/04/2020 06:09:53",
    "XML ID": "974",
    "Total Lag": "0.9707871",
    "Create Lag": "0.6979458",
    "Process Lag": "0.2728413"
  },
  {
    "stopID": "33",
    "stopQueryDate": "2020-04-30T05:10:01.476Z",
    "Direction": "Outbound",
    "Destination": "Bride's Glen",
    "Time": "00:19:07",
    "AVLS": "00:19:47",
    "Tram": "5013",
    "Action": "a",
    "Msg Sent": "30/04/2020 06:09:53",
    "Msg Received": "30/04/2020 06:09:53",
    "Msg Processed": "30/04/2020 06:09:53",
    "XML ID": "974",
    "Total Lag": "0.9707871",
    "Create Lag": "0.6979458",
    "Process Lag": "0.2728413"
  },
  {
    "stopID": "33",
    "stopQueryDate": "2020-04-30T05:10:01.476Z",
    "Direction": "Outbound",
    "Destination": "Bride's Glen",
    "Time": "00:19:07",
    "AVLS": "00:19:47",
    "Tram": "5013",
    "Action": "a",
    "Msg Sent": "30/04/2020 06:09:53",
    "Msg Received": "30/04/2020 06:09:53",
    "Msg Processed": "30/04/2020 06:09:53",
    "XML ID": "974",
    "Total Lag": "0.9707871",
    "Create Lag": "0.6979458",
    "Process Lag": "0.2728413"
  },
  {
    "stopID": "42",
    "stopQueryDate": "2020-04-30T05:10:01.483Z",
    "Direction": "Outbound",
    "Destination": "Bride's Glen",
    "Time": "00:12:31",
    "AVLS": "00:13:11",
    "Tram": "5005",
    "Action": "a",
    "Msg Sent": "30/04/2020 06:09:53",
    "Msg Received": "30/04/2020 06:09:53",
    "Msg Processed": "30/04/2020 06:09:53",
    "XML ID": "974",
    "Total Lag": "0.8590681",
    "Create Lag": "0.6979458",
    "Process Lag": "0.1611223"
  },
  {
    "stopID": "42",
    "stopQueryDate": "2020-04-30T05:10:01.483Z",
    "Direction": "Outbound",
    "Destination": "Bride's Glen",
    "Time": "00:12:31",
    "AVLS": "00:13:11",
    "Tram": "5005",
    "Action": "a",
    "Msg Sent": "30/04/2020 06:09:53",
    "Msg Received": "30/04/2020 06:09:53",
    "Msg Processed": "30/04/2020 06:09:53",
    "XML ID": "974",
    "Total Lag": "0.8590681",
    "Create Lag": "0.6979458",
    "Process Lag": "0.1611223"
  },
  {
    "stopID": "42",
    "stopQueryDate": "2020-04-30T05:10:01.483Z",
    "Direction": "Outbound",
    "Destination": "Bride's Glen",
    "Time": "00:12:31",
    "AVLS": "00:13:11",
    "Tram": "5005",
    "Action": "a",
    "Msg Sent": "30/04/2020 06:09:53",
    "Msg Received": "30/04/2020 06:09:53",
    "Msg Processed": "30/04/2020 06:09:53",
    "XML ID": "974",
    "Total Lag": "0.8590681",
    "Create Lag": "0.6979458",
    "Process Lag": "0.1611223"
  },
  {
    "stopID": "43",
    "stopQueryDate": "2020-04-30T05:10:01.492Z",
    "Direction": "Outbound",
    "Destination": "Bride's Glen",
    "Time": "00:14:04",
    "AVLS": "00:14:44",
    "Tram": "5005",
    "Action": "a",
    "Msg Sent": "30/04/2020 06:09:53",
    "Msg Received": "30/04/2020 06:09:53",
    "Msg Processed": "30/04/2020 06:09:53",
    "XML ID": "974",
    "Total Lag": "0.8746911",
    "Create Lag": "0.6979458",
    "Process Lag": "0.1767453"
  },
  {
    "stopID": "43",
    "stopQueryDate": "2020-04-30T05:10:01.492Z",
    "Direction": "Outbound",
    "Destination": "Bride's Glen",
    "Time": "00:14:04",
    "AVLS": "00:14:44",
    "Tram": "5005",
    "Action": "a",
    "Msg Sent": "30/04/2020 06:09:53",
    "Msg Received": "30/04/2020 06:09:53",
    "Msg Processed": "30/04/2020 06:09:53",
    "XML ID": "974",
    "Total Lag": "0.8746911",
    "Create Lag": "0.6979458",
    "Process Lag": "0.1767453"
  },
  {
    "stopID": "43",
    "stopQueryDate": "2020-04-30T05:10:01.492Z",
    "Direction": "Outbound",
    "Destination": "Bride's Glen",
    "Time": "00:14:04",
    "AVLS": "00:14:44",
    "Tram": "5005",
    "Action": "a",
    "Msg Sent": "30/04/2020 06:09:53",
    "Msg Received": "30/04/2020 06:09:53",
    "Msg Processed": "30/04/2020 06:09:53",
    "XML ID": "974",
    "Total Lag": "0.8746911",
    "Create Lag": "0.6979458",
    "Process Lag": "0.1767453"
  },
  {
    "stopID": "43",
    "stopQueryDate": "2020-04-30T05:10:01.492Z",
    "Direction": "Outbound",
    "Destination": "Bride's Glen",
    "Time": "00:14:04",
    "AVLS": "00:14:44",
    "Tram": "5005",
    "Action": "a",
    "Msg Sent": "30/04/2020 06:09:53",
    "Msg Received": "30/04/2020 06:09:53",
    "Msg Processed": "30/04/2020 06:09:53",
    "XML ID": "974",
    "Total Lag": "0.8746911",
    "Create Lag": "0.6979458",
    "Process Lag": "0.1767453"
  },
  {
    "stopID": "53",
    "stopQueryDate": "2020-04-30T05:10:01.503Z",
    "Direction": "Terminating",
    "Destination": "Saggart",
    "Time": "00:17:27",
    "AVLS": "00:18:07",
    "Tram": "3019",
    "Action": "a",
    "Msg Sent": "30/04/2020 06:09:53",
    "Msg Received": "30/04/2020 06:09:53",
    "Msg Processed": "30/04/2020 06:09:53",
    "XML ID": "973",
    "Total Lag": "0.5549975",
    "Create Lag": "0.3471688",
    "Process Lag": "0.2078287"
  },
  {
    "stopID": "53",
    "stopQueryDate": "2020-04-30T05:10:01.503Z",
    "Direction": "Terminating",
    "Destination": "Saggart",
    "Time": "00:17:27",
    "AVLS": "00:18:07",
    "Tram": "3019",
    "Action": "a",
    "Msg Sent": "30/04/2020 06:09:53",
    "Msg Received": "30/04/2020 06:09:53",
    "Msg Processed": "30/04/2020 06:09:53",
    "XML ID": "973",
    "Total Lag": "0.5549975",
    "Create Lag": "0.3471688",
    "Process Lag": "0.2078287"
  },
  {
    "stopID": "53",
    "stopQueryDate": "2020-04-30T05:10:01.503Z",
    "Direction": "Terminating",
    "Destination": "Saggart",
    "Time": "00:17:27",
    "AVLS": "00:18:07",
    "Tram": "3019",
    "Action": "a",
    "Msg Sent": "30/04/2020 06:09:53",
    "Msg Received": "30/04/2020 06:09:53",
    "Msg Processed": "30/04/2020 06:09:53",
    "XML ID": "973",
    "Total Lag": "0.5549975",
    "Create Lag": "0.3471688",
    "Process Lag": "0.2078287"
  },
  {
    "stopID": "53",
    "stopQueryDate": "2020-04-30T05:10:01.503Z",
    "Direction": "Terminating",
    "Destination": "Saggart",
    "Time": "00:17:27",
    "AVLS": "00:18:07",
    "Tram": "3019",
    "Action": "a",
    "Msg Sent": "30/04/2020 06:09:53",
    "Msg Received": "30/04/2020 06:09:53",
    "Msg Processed": "30/04/2020 06:09:53",
    "XML ID": "973",
    "Total Lag": "0.5549975",
    "Create Lag": "0.3471688",
    "Process Lag": "0.2078287"
  },
  {
    "stopID": "53",
    "stopQueryDate": "2020-04-30T05:10:01.503Z",
    "Direction": "Terminating",
    "Destination": "Saggart",
    "Time": "00:17:27",
    "AVLS": "00:18:07",
    "Tram": "3019",
    "Action": "a",
    "Msg Sent": "30/04/2020 06:09:53",
    "Msg Received": "30/04/2020 06:09:53",
    "Msg Processed": "30/04/2020 06:09:53",
    "XML ID": "973",
    "Total Lag": "0.5549975",
    "Create Lag": "0.3471688",
    "Process Lag": "0.2078287"
  },
  {
    "stopID": "29",
    "stopQueryDate": "2020-04-30T05:10:01.511Z",
    "Direction": "Outbound",
    "Destination": "Bride's Glen",
    "Time": "00:12:09",
    "AVLS": "00:12:49",
    "Tram": "5013",
    "Action": "a",
    "Msg Sent": "30/04/2020 06:09:53",
    "Msg Received": "30/04/2020 06:09:53",
    "Msg Processed": "30/04/2020 06:09:53",
    "XML ID": "974",
    "Total Lag": "0.9551924",
    "Create Lag": "0.6979458",
    "Process Lag": "0.2572466"
  },
  {
    "stopID": "29",
    "stopQueryDate": "2020-04-30T05:10:01.511Z",
    "Direction": "Outbound",
    "Destination": "Bride's Glen",
    "Time": "00:12:09",
    "AVLS": "00:12:49",
    "Tram": "5013",
    "Action": "a",
    "Msg Sent": "30/04/2020 06:09:53",
    "Msg Received": "30/04/2020 06:09:53",
    "Msg Processed": "30/04/2020 06:09:53",
    "XML ID": "974",
    "Total Lag": "0.9551924",
    "Create Lag": "0.6979458",
    "Process Lag": "0.2572466"
  },
  {
    "stopID": "29",
    "stopQueryDate": "2020-04-30T05:10:01.511Z",
    "Direction": "Outbound",
    "Destination": "Bride's Glen",
    "Time": "00:12:09",
    "AVLS": "00:12:49",
    "Tram": "5013",
    "Action": "a",
    "Msg Sent": "30/04/2020 06:09:53",
    "Msg Received": "30/04/2020 06:09:53",
    "Msg Processed": "30/04/2020 06:09:53",
    "XML ID": "974",
    "Total Lag": "0.9551924",
    "Create Lag": "0.6979458",
    "Process Lag": "0.2572466"
  },
  {
    "stopID": "29",
    "stopQueryDate": "2020-04-30T05:10:01.511Z",
    "Direction": "Outbound",
    "Destination": "Bride's Glen",
    "Time": "00:12:09",
    "AVLS": "00:12:49",
    "Tram": "5013",
    "Action": "a",
    "Msg Sent": "30/04/2020 06:09:53",
    "Msg Received": "30/04/2020 06:09:53",
    "Msg Processed": "30/04/2020 06:09:53",
    "XML ID": "974",
    "Total Lag": "0.9551924",
    "Create Lag": "0.6979458",
    "Process Lag": "0.2572466"
  }
]